<?xml version="1.0" encoding="UTF-8"?>
<manuscript>
	<contour>
		<point>
			<x>203.812765957</x>
			<y>104.0</y>
		</point>
		<point>
			<x>203.824786325</x>
			<y>103.0</y>
		</point>
		<point>
			<x>204.0</x>
			<y>102.832653061</y>
		</point>
		<point>
			<x>205.0</x>
			<y>102.832599119</y>
		</point>
		<point>
			<x>205.807692308</x>
			<y>102.0</y>
		</point>
		<point>
			<x>206.0</x>
			<y>101.819277108</y>
		</point>
		<point>
			<x>206.8</x>
			<y>101.0</y>
		</point>
		<point>
			<x>207.0</x>
			<y>100.795180723</y>
		</point>
		<point>
			<x>208.0</x>
			<y>100.836134454</y>
		</point>
		<point>
			<x>208.805668016</x>
			<y>100.0</y>
		</point>
		<point>
			<x>209.0</x>
			<y>99.8</y>
		</point>
		<point>
			<x>210.0</x>
			<y>99.8644067797</y>
		</point>
		<point>
			<x>211.0</x>
			<y>99.8017241379</y>
		</point>
		<point>
			<x>211.812227074</x>
			<y>99.0</y>
		</point>
		<point>
			<x>212.0</x>
			<y>98.8185654008</y>
		</point>
		<point>
			<x>213.0</x>
			<y>98.8217391304</y>
		</point>
		<point>
			<x>214.0</x>
			<y>98.8</y>
		</point>
		<point>
			<x>215.0</x>
			<y>98.8031496063</y>
		</point>
		<point>
			<x>216.0</x>
			<y>98.8899521531</y>
		</point>
		<point>
			<x>217.0</x>
			<y>98.8</y>
		</point>
		<point>
			<x>218.0</x>
			<y>98.8</y>
		</point>
		<point>
			<x>219.0</x>
			<y>98.8165938865</y>
		</point>
		<point>
			<x>220.0</x>
			<y>98.796</y>
		</point>
		<point>
			<x>221.0</x>
			<y>98.8973214286</y>
		</point>
		<point>
			<x>221.797619048</x>
			<y>98.0</y>
		</point>
		<point>
			<x>222.0</x>
			<y>97.7901234568</y>
		</point>
		<point>
			<x>223.0</x>
			<y>97.812749004</y>
		</point>
		<point>
			<x>223.816</x>
			<y>97.0</y>
		</point>
		<point>
			<x>223.808510638</x>
			<y>96.0</y>
		</point>
		<point>
			<x>224.0</x>
			<y>95.8192771084</y>
		</point>
		<point>
			<x>224.8</x>
			<y>95.0</y>
		</point>
		<point>
			<x>225.0</x>
			<y>94.7976190476</y>
		</point>
		<point>
			<x>225.905405405</x>
			<y>94.0</y>
		</point>
		<point>
			<x>225.805555556</x>
			<y>93.0</y>
		</point>
		<point>
			<x>226.0</x>
			<y>92.7991803279</y>
		</point>
		<point>
			<x>227.0</x>
			<y>92.8</y>
		</point>
		<point>
			<x>227.846473029</x>
			<y>92.0</y>
		</point>
		<point>
			<x>227.798418972</x>
			<y>91.0</y>
		</point>
		<point>
			<x>227.819742489</x>
			<y>90.0</y>
		</point>
		<point>
			<x>227.815450644</x>
			<y>89.0</y>
		</point>
		<point>
			<x>227.796747967</x>
			<y>88.0</y>
		</point>
		<point>
			<x>227.0</x>
			<y>87.2064777328</y>
		</point>
		<point>
			<x>226.8</x>
			<y>87.0</y>
		</point>
		<point>
			<x>226.0</x>
			<y>86.2</y>
		</point>
		<point>
			<x>225.797619048</x>
			<y>86.0</y>
		</point>
		<point>
			<x>225.0</x>
			<y>85.1992031873</y>
		</point>
		<point>
			<x>224.0</x>
			<y>85.2</y>
		</point>
		<point>
			<x>223.8</x>
			<y>85.0</y>
		</point>
		<point>
			<x>223.0</x>
			<y>84.2</y>
		</point>
		<point>
			<x>222.0</x>
			<y>84.2125</y>
		</point>
		<point>
			<x>221.0</x>
			<y>84.2</y>
		</point>
		<point>
			<x>220.0</x>
			<y>84.204</y>
		</point>
		<point>
			<x>219.794354839</x>
			<y>84.0</y>
		</point>
		<point>
			<x>219.804780876</x>
			<y>83.0</y>
		</point>
		<point>
			<x>219.0</x>
			<y>82.1984126984</y>
		</point>
		<point>
			<x>218.0</x>
			<y>82.2007874016</y>
		</point>
		<point>
			<x>217.0</x>
			<y>82.1666666667</y>
		</point>
		<point>
			<x>216.0</x>
			<y>82.2</y>
		</point>
		<point>
			<x>215.0</x>
			<y>82.1473214286</y>
		</point>
		<point>
			<x>214.85</x>
			<y>82.0</y>
		</point>
		<point>
			<x>214.0</x>
			<y>81.1834061135</y>
		</point>
		<point>
			<x>213.0</x>
			<y>81.1688311688</y>
		</point>
		<point>
			<x>212.0</x>
			<y>81.2</y>
		</point>
		<point>
			<x>211.8</x>
			<y>81.0</y>
		</point>
		<point>
			<x>212.0</x>
			<y>80.7951807229</y>
		</point>
		<point>
			<x>212.795180723</x>
			<y>80.0</y>
		</point>
		<point>
			<x>212.0</x>
			<y>79.0917431193</y>
		</point>
		<point>
			<x>211.0</x>
			<y>79.2023809524</y>
		</point>
		<point>
			<x>210.0</x>
			<y>79.1830357143</y>
		</point>
		<point>
			<x>209.0</x>
			<y>79.187755102</y>
		</point>
		<point>
			<x>208.810699588</x>
			<y>79.0</y>
		</point>
		<point>
			<x>209.0</x>
			<y>78.8114754098</y>
		</point>
		<point>
			<x>209.835443038</x>
			<y>78.0</y>
		</point>
		<point>
			<x>209.0</x>
			<y>77.1715481172</y>
		</point>
		<point>
			<x>208.198380567</x>
			<y>78.0</y>
		</point>
		<point>
			<x>208.0</x>
			<y>78.1991869919</y>
		</point>
		<point>
			<x>207.0</x>
			<y>78.2</y>
		</point>
		<point>
			<x>206.0</x>
			<y>78.1752136752</y>
		</point>
		<point>
			<x>205.0</x>
			<y>78.1842105263</y>
		</point>
		<point>
			<x>204.0</x>
			<y>78.2</y>
		</point>
		<point>
			<x>203.8</x>
			<y>78.0</y>
		</point>
		<point>
			<x>203.0</x>
			<y>77.2</y>
		</point>
		<point>
			<x>202.0</x>
			<y>77.1761658031</y>
		</point>
		<point>
			<x>201.857142857</x>
			<y>77.0</y>
		</point>
		<point>
			<x>201.0</x>
			<y>76.1936758893</y>
		</point>
		<point>
			<x>200.795833333</x>
			<y>76.0</y>
		</point>
		<point>
			<x>200.822580645</x>
			<y>75.0</y>
		</point>
		<point>
			<x>201.0</x>
			<y>74.8225806452</y>
		</point>
		<point>
			<x>202.0</x>
			<y>74.8</y>
		</point>
		<point>
			<x>202.816</x>
			<y>74.0</y>
		</point>
		<point>
			<x>202.0</x>
			<y>73.2</y>
		</point>
		<point>
			<x>201.0</x>
			<y>73.1604938272</y>
		</point>
		<point>
			<x>200.0</x>
			<y>73.1197916667</y>
		</point>
		<point>
			<x>199.0</x>
			<y>73.2064777328</y>
		</point>
		<point>
			<x>198.0</x>
			<y>73.2</y>
		</point>
		<point>
			<x>197.791836735</x>
			<y>73.0</y>
		</point>
		<point>
			<x>197.0</x>
			<y>72.1983471074</y>
		</point>
		<point>
			<x>196.18487395</x>
			<y>73.0</y>
		</point>
		<point>
			<x>196.0</x>
			<y>73.186440678</y>
		</point>
		<point>
			<x>195.193277311</x>
			<y>74.0</y>
		</point>
		<point>
			<x>195.19047619</x>
			<y>75.0</y>
		</point>
		<point>
			<x>195.200819672</x>
			<y>76.0</y>
		</point>
		<point>
			<x>195.0</x>
			<y>76.196</y>
		</point>
		<point>
			<x>194.0</x>
			<y>76.2</y>
		</point>
		<point>
			<x>193.0</x>
			<y>76.2073170732</y>
		</point>
		<point>
			<x>192.207317073</x>
			<y>77.0</y>
		</point>
		<point>
			<x>192.153846154</x>
			<y>78.0</y>
		</point>
		<point>
			<x>192.209016393</x>
			<y>79.0</y>
		</point>
		<point>
			<x>192.172995781</x>
			<y>80.0</y>
		</point>
		<point>
			<x>193.0</x>
			<y>80.8270042194</y>
		</point>
		<point>
			<x>193.188940092</x>
			<y>81.0</y>
		</point>
		<point>
			<x>193.202380952</x>
			<y>82.0</y>
		</point>
		<point>
			<x>194.0</x>
			<y>82.8305785124</y>
		</point>
		<point>
			<x>194.177489177</x>
			<y>83.0</y>
		</point>
		<point>
			<x>195.0</x>
			<y>83.7883817427</y>
		</point>
		<point>
			<x>195.2</x>
			<y>84.0</y>
		</point>
		<point>
			<x>195.168032787</x>
			<y>85.0</y>
		</point>
		<point>
			<x>196.0</x>
			<y>85.7992125984</y>
		</point>
		<point>
			<x>197.0</x>
			<y>85.8476190476</y>
		</point>
		<point>
			<x>198.0</x>
			<y>85.8056680162</y>
		</point>
		<point>
			<x>198.206896552</x>
			<y>86.0</y>
		</point>
		<point>
			<x>199.0</x>
			<y>86.8</y>
		</point>
		<point>
			<x>200.0</x>
			<y>86.7926829268</y>
		</point>
		<point>
			<x>201.0</x>
			<y>86.8281938326</y>
		</point>
		<point>
			<x>202.0</x>
			<y>86.8</y>
		</point>
		<point>
			<x>202.201581028</x>
			<y>87.0</y>
		</point>
		<point>
			<x>202.0</x>
			<y>87.2015810277</y>
		</point>
		<point>
			<x>201.0</x>
			<y>87.1611570248</y>
		</point>
		<point>
			<x>200.0</x>
			<y>87.2007874016</y>
		</point>
		<point>
			<x>199.0</x>
			<y>87.1847389558</y>
		</point>
		<point>
			<x>198.0</x>
			<y>87.1742738589</y>
		</point>
		<point>
			<x>197.0</x>
			<y>87.2081632653</y>
		</point>
		<point>
			<x>196.0</x>
			<y>87.1255605381</y>
		</point>
		<point>
			<x>195.190871369</x>
			<y>88.0</y>
		</point>
		<point>
			<x>195.0</x>
			<y>88.1900826446</y>
		</point>
		<point>
			<x>194.0</x>
			<y>88.1859504132</y>
		</point>
		<point>
			<x>193.0</x>
			<y>88.1976284585</y>
		</point>
		<point>
			<x>192.0</x>
			<y>88.2</y>
		</point>
		<point>
			<x>191.0</x>
			<y>88.2016129032</y>
		</point>
		<point>
			<x>190.0</x>
			<y>88.2016129032</y>
		</point>
		<point>
			<x>189.0</x>
			<y>88.1975806452</y>
		</point>
		<point>
			<x>188.0</x>
			<y>88.1975806452</y>
		</point>
		<point>
			<x>187.0</x>
			<y>88.1943319838</y>
		</point>
		<point>
			<x>186.0</x>
			<y>88.1943319838</y>
		</point>
		<point>
			<x>185.0</x>
			<y>88.1943319838</y>
		</point>
		<point>
			<x>184.0</x>
			<y>88.1910569106</y>
		</point>
		<point>
			<x>183.0</x>
			<y>88.1992031873</y>
		</point>
		<point>
			<x>182.0</x>
			<y>88.1936758893</y>
		</point>
		<point>
			<x>181.0</x>
			<y>88.1791666667</y>
		</point>
		<point>
			<x>180.0</x>
			<y>88.2</y>
		</point>
		<point>
			<x>179.2</x>
			<y>89.0</y>
		</point>
		<point>
			<x>179.0</x>
			<y>89.2</y>
		</point>
		<point>
			<x>178.0</x>
			<y>89.184</y>
		</point>
		<point>
			<x>177.0</x>
			<y>89.2073170732</y>
		</point>
		<point>
			<x>176.0</x>
			<y>89.1968503937</y>
		</point>
		<point>
			<x>175.0</x>
			<y>89.2</y>
		</point>
		<point>
			<x>174.0</x>
			<y>89.2</y>
		</point>
		<point>
			<x>173.0</x>
			<y>89.2</y>
		</point>
		<point>
			<x>172.0</x>
			<y>89.2</y>
		</point>
		<point>
			<x>171.0</x>
			<y>89.2</y>
		</point>
		<point>
			<x>170.0</x>
			<y>89.2</y>
		</point>
		<point>
			<x>169.0</x>
			<y>89.2</y>
		</point>
		<point>
			<x>168.0</x>
			<y>89.2</y>
		</point>
		<point>
			<x>167.0</x>
			<y>89.1936758893</y>
		</point>
		<point>
			<x>166.0</x>
			<y>89.2</y>
		</point>
		<point>
			<x>165.0</x>
			<y>89.2007874016</y>
		</point>
		<point>
			<x>164.0</x>
			<y>89.2015810277</y>
		</point>
		<point>
			<x>163.0</x>
			<y>89.2023809524</y>
		</point>
		<point>
			<x>162.0</x>
			<y>89.2023809524</y>
		</point>
		<point>
			<x>161.0</x>
			<y>89.1927710843</y>
		</point>
		<point>
			<x>160.0</x>
			<y>89.185483871</y>
		</point>
		<point>
			<x>159.201581028</x>
			<y>90.0</y>
		</point>
		<point>
			<x>159.0</x>
			<y>90.2</y>
		</point>
		<point>
			<x>158.0</x>
			<y>90.1932773109</y>
		</point>
		<point>
			<x>157.0</x>
			<y>90.1837606838</y>
		</point>
		<point>
			<x>156.0</x>
			<y>90.2</y>
		</point>
		<point>
			<x>155.8</x>
			<y>90.0</y>
		</point>
		<point>
			<x>155.0</x>
			<y>89.1774193548</y>
		</point>
		<point>
			<x>154.0</x>
			<y>89.2086956522</y>
		</point>
		<point>
			<x>153.0</x>
			<y>89.2041666667</y>
		</point>
		<point>
			<x>152.0</x>
			<y>89.1968503937</y>
		</point>
		<point>
			<x>151.0</x>
			<y>89.2</y>
		</point>
		<point>
			<x>150.187250996</x>
			<y>90.0</y>
		</point>
		<point>
			<x>150.0</x>
			<y>90.1950207469</y>
		</point>
		<point>
			<x>149.0</x>
			<y>90.1936758893</y>
		</point>
		<point>
			<x>148.0</x>
			<y>90.1198156682</y>
		</point>
		<point>
			<x>147.0</x>
			<y>90.1759656652</y>
		</point>
		<point>
			<x>146.0</x>
			<y>90.1680327869</y>
		</point>
		<point>
			<x>145.0</x>
			<y>90.2081632653</y>
		</point>
		<point>
			<x>144.0</x>
			<y>90.1719457014</y>
		</point>
		<point>
			<x>143.136792453</x>
			<y>91.0</y>
		</point>
		<point>
			<x>143.2</x>
			<y>92.0</y>
		</point>
		<point>
			<x>143.0</x>
			<y>92.2161016949</y>
		</point>
		<point>
			<x>142.0</x>
			<y>92.1392405063</y>
		</point>
		<point>
			<x>141.2</x>
			<y>93.0</y>
		</point>
		<point>
			<x>141.157024793</x>
			<y>94.0</y>
		</point>
		<point>
			<x>141.0</x>
			<y>94.1570247934</y>
		</point>
		<point>
			<x>140.184</x>
			<y>95.0</y>
		</point>
		<point>
			<x>140.2</x>
			<y>96.0</y>
		</point>
		<point>
			<x>140.15</x>
			<y>97.0</y>
		</point>
		<point>
			<x>140.0</x>
			<y>97.1572052402</y>
		</point>
		<point>
			<x>139.18220339</x>
			<y>98.0</y>
		</point>
		<point>
			<x>139.203187251</x>
			<y>99.0</y>
		</point>
		<point>
			<x>140.0</x>
			<y>99.8333333333</y>
		</point>
		<point>
			<x>140.164609053</x>
			<y>100.0</y>
		</point>
		<point>
			<x>141.0</x>
			<y>100.815261044</y>
		</point>
		<point>
			<x>141.184</x>
			<y>101.0</y>
		</point>
		<point>
			<x>142.0</x>
			<y>101.8</y>
		</point>
		<point>
			<x>143.0</x>
			<y>101.8</y>
		</point>
		<point>
			<x>144.0</x>
			<y>101.832653061</y>
		</point>
		<point>
			<x>144.8</x>
			<y>101.0</y>
		</point>
		<point>
			<x>145.0</x>
			<y>100.797619048</y>
		</point>
		<point>
			<x>146.0</x>
			<y>100.866359447</y>
		</point>
		<point>
			<x>147.0</x>
			<y>100.827160494</y>
		</point>
		<point>
			<x>148.0</x>
			<y>100.7875</y>
		</point>
		<point>
			<x>148.870967742</x>
			<y>100.0</y>
		</point>
		<point>
			<x>149.0</x>
			<y>99.8685446009</y>
		</point>
		<point>
			<x>150.0</x>
			<y>99.7918367347</y>
		</point>
		<point>
			<x>151.0</x>
			<y>99.8326530612</y>
		</point>
		<point>
			<x>152.0</x>
			<y>99.8</y>
		</point>
		<point>
			<x>153.0</x>
			<y>99.8086124402</y>
		</point>
		<point>
			<x>154.0</x>
			<y>99.8535564854</y>
		</point>
		<point>
			<x>155.0</x>
			<y>99.7926829268</y>
		</point>
		<point>
			<x>156.0</x>
			<y>99.8697674419</y>
		</point>
		<point>
			<x>156.861751152</x>
			<y>99.0</y>
		</point>
		<point>
			<x>157.0</x>
			<y>98.8648648649</y>
		</point>
		<point>
			<x>158.0</x>
			<y>98.8</y>
		</point>
		<point>
			<x>159.0</x>
			<y>98.846473029</y>
		</point>
		<point>
			<x>160.0</x>
			<y>98.7991967871</y>
		</point>
		<point>
			<x>161.0</x>
			<y>98.7991967871</y>
		</point>
		<point>
			<x>162.0</x>
			<y>98.796</y>
		</point>
		<point>
			<x>163.0</x>
			<y>98.796</y>
		</point>
		<point>
			<x>164.0</x>
			<y>98.796</y>
		</point>
		<point>
			<x>165.0</x>
			<y>98.796</y>
		</point>
		<point>
			<x>166.0</x>
			<y>98.796</y>
		</point>
		<point>
			<x>167.0</x>
			<y>98.796</y>
		</point>
		<point>
			<x>168.0</x>
			<y>98.8</y>
		</point>
		<point>
			<x>169.0</x>
			<y>98.8</y>
		</point>
		<point>
			<x>170.0</x>
			<y>98.8170212766</y>
		</point>
		<point>
			<x>171.0</x>
			<y>98.8</y>
		</point>
		<point>
			<x>171.8</x>
			<y>98.0</y>
		</point>
		<point>
			<x>172.0</x>
			<y>97.8</y>
		</point>
		<point>
			<x>173.0</x>
			<y>97.8565400844</y>
		</point>
		<point>
			<x>174.0</x>
			<y>97.7918367347</y>
		</point>
		<point>
			<x>175.0</x>
			<y>97.8</y>
		</point>
		<point>
			<x>176.0</x>
			<y>97.7992125984</y>
		</point>
		<point>
			<x>177.0</x>
			<y>97.7992125984</y>
		</point>
		<point>
			<x>178.0</x>
			<y>97.7992125984</y>
		</point>
		<point>
			<x>179.0</x>
			<y>97.7992125984</y>
		</point>
		<point>
			<x>180.0</x>
			<y>97.7992125984</y>
		</point>
		<point>
			<x>181.0</x>
			<y>97.7992125984</y>
		</point>
		<point>
			<x>182.0</x>
			<y>97.7992125984</y>
		</point>
		<point>
			<x>183.0</x>
			<y>97.7992125984</y>
		</point>
		<point>
			<x>184.0</x>
			<y>97.8056680162</y>
		</point>
		<point>
			<x>185.0</x>
			<y>97.8056680162</y>
		</point>
		<point>
			<x>186.0</x>
			<y>97.8056680162</y>
		</point>
		<point>
			<x>187.0</x>
			<y>97.8056680162</y>
		</point>
		<point>
			<x>188.0</x>
			<y>97.8081632653</y>
		</point>
		<point>
			<x>189.0</x>
			<y>97.8081632653</y>
		</point>
		<point>
			<x>190.0</x>
			<y>97.8081632653</y>
		</point>
		<point>
			<x>191.0</x>
			<y>97.8081632653</y>
		</point>
		<point>
			<x>192.0</x>
			<y>97.825203252</y>
		</point>
		<point>
			<x>193.0</x>
			<y>97.7838983051</y>
		</point>
		<point>
			<x>194.0</x>
			<y>97.866359447</y>
		</point>
		<point>
			<x>194.125541126</x>
			<y>98.0</y>
		</point>
		<point>
			<x>195.0</x>
			<y>98.7984189723</y>
		</point>
		<point>
			<x>195.205645161</x>
			<y>99.0</y>
		</point>
		<point>
			<x>195.0</x>
			<y>99.2</y>
		</point>
		<point>
			<x>194.2</x>
			<y>100.0</y>
		</point>
		<point>
			<x>195.0</x>
			<y>100.8</y>
		</point>
		<point>
			<x>195.203187251</x>
			<y>101.0</y>
		</point>
		<point>
			<x>195.15</x>
			<y>102.0</y>
		</point>
		<point>
			<x>195.204819277</x>
			<y>103.0</y>
		</point>
		<point>
			<x>196.0</x>
			<y>103.814814815</y>
		</point>
		<point>
			<x>197.0</x>
			<y>103.895454545</y>
		</point>
		<point>
			<x>197.111650485</x>
			<y>104.0</y>
		</point>
		<point>
			<x>198.0</x>
			<y>104.871428571</y>
		</point>
		<point>
			<x>199.0</x>
			<y>104.8</y>
		</point>
		<point>
			<x>200.0</x>
			<y>104.838983051</y>
		</point>
		<point>
			<x>201.0</x>
			<y>104.8</y>
		</point>
		<point>
			<x>202.0</x>
			<y>104.85915493</y>
		</point>
		<point>
			<x>203.0</x>
			<y>104.830434783</y>
		</point>
		<point>
			<x>203.812765957</x>
			<y>104.0</y>
		</point>
	</contour>
	<contour>
		<point>
			<x>69.8</x>
			<y>116.0</y>
		</point>
		<point>
			<x>69.8</x>
			<y>115.0</y>
		</point>
		<point>
			<x>70.0</x>
			<y>114.794354839</y>
		</point>
		<point>
			<x>70.7943548387</x>
			<y>114.0</y>
		</point>
		<point>
			<x>71.0</x>
			<y>113.790983607</y>
		</point>
		<point>
			<x>71.8075313808</x>
			<y>113.0</y>
		</point>
		<point>
			<x>71.812244898</x>
			<y>112.0</y>
		</point>
		<point>
			<x>71.7905982906</x>
			<y>111.0</y>
		</point>
		<point>
			<x>71.8225806452</x>
			<y>110.0</y>
		</point>
		<point>
			<x>71.7792207792</x>
			<y>109.0</y>
		</point>
		<point>
			<x>71.0</x>
			<y>108.150943396</y>
		</point>
		<point>
			<x>70.8558558559</x>
			<y>108.0</y>
		</point>
		<point>
			<x>70.7976190476</x>
			<y>107.0</y>
		</point>
		<point>
			<x>70.8259109312</x>
			<y>106.0</y>
		</point>
		<point>
			<x>70.7984189723</x>
			<y>105.0</y>
		</point>
		<point>
			<x>71.0</x>
			<y>104.794354839</y>
		</point>
		<point>
			<x>72.0</x>
			<y>104.8</y>
		</point>
		<point>
			<x>72.2</x>
			<y>105.0</y>
		</point>
		<point>
			<x>73.0</x>
			<y>105.8</y>
		</point>
		<point>
			<x>74.0</x>
			<y>105.848341232</y>
		</point>
		<point>
			<x>75.0</x>
			<y>105.800796813</y>
		</point>
		<point>
			<x>76.0</x>
			<y>105.8</y>
		</point>
		<point>
			<x>76.2107438017</x>
			<y>106.0</y>
		</point>
		<point>
			<x>77.0</x>
			<y>106.841409692</y>
		</point>
		<point>
			<x>78.0</x>
			<y>106.798418972</y>
		</point>
		<point>
			<x>79.0</x>
			<y>106.8</y>
		</point>
		<point>
			<x>79.8</x>
			<y>106.0</y>
		</point>
		<point>
			<x>80.0</x>
			<y>105.8</y>
		</point>
		<point>
			<x>81.0</x>
			<y>105.8</y>
		</point>
		<point>
			<x>82.0</x>
			<y>105.844537815</y>
		</point>
		<point>
			<x>82.1778846154</x>
			<y>106.0</y>
		</point>
		<point>
			<x>83.0</x>
			<y>106.818181818</y>
		</point>
		<point>
			<x>84.0</x>
			<y>106.834024896</y>
		</point>
		<point>
			<x>84.1687763713</x>
			<y>107.0</y>
		</point>
		<point>
			<x>84.2246696035</x>
			<y>108.0</y>
		</point>
		<point>
			<x>85.0</x>
			<y>108.926315789</y>
		</point>
		<point>
			<x>86.0</x>
			<y>108.8</y>
		</point>
		<point>
			<x>86.2</x>
			<y>109.0</y>
		</point>
		<point>
			<x>87.0</x>
			<y>109.8</y>
		</point>
		<point>
			<x>87.2073170732</x>
			<y>110.0</y>
		</point>
		<point>
			<x>88.0</x>
			<y>110.819327731</y>
		</point>
		<point>
			<x>89.0</x>
			<y>110.793522267</y>
		</point>
		<point>
			<x>90.0</x>
			<y>110.802419355</y>
		</point>
		<point>
			<x>91.0</x>
			<y>110.80952381</y>
		</point>
		<point>
			<x>91.1991701245</x>
			<y>111.0</y>
		</point>
		<point>
			<x>92.0</x>
			<y>111.861607143</y>
		</point>
		<point>
			<x>93.0</x>
			<y>111.793522267</y>
		</point>
		<point>
			<x>94.0</x>
			<y>111.839506173</y>
		</point>
		<point>
			<x>94.164556962</x>
			<y>112.0</y>
		</point>
		<point>
			<x>95.0</x>
			<y>112.828451883</y>
		</point>
		<point>
			<x>96.0</x>
			<y>112.804166667</y>
		</point>
		<point>
			<x>96.8427947598</x>
			<y>112.0</y>
		</point>
		<point>
			<x>97.0</x>
			<y>111.847457627</y>
		</point>
		<point>
			<x>98.0</x>
			<y>111.790983607</y>
		</point>
		<point>
			<x>99.0</x>
			<y>111.930693069</y>
		</point>
		<point>
			<x>100.0</x>
			<y>111.796812749</y>
		</point>
		<point>
			<x>101.0</x>
			<y>111.8</y>
		</point>
		<point>
			<x>102.0</x>
			<y>111.840707965</y>
		</point>
		<point>
			<x>102.791666667</x>
			<y>111.0</y>
		</point>
		<point>
			<x>103.0</x>
			<y>110.787234043</y>
		</point>
		<point>
			<x>103.829596413</x>
			<y>110.0</y>
		</point>
		<point>
			<x>104.0</x>
			<y>109.842975207</y>
		</point>
		<point>
			<x>104.819277108</x>
			<y>109.0</y>
		</point>
		<point>
			<x>105.0</x>
			<y>108.817073171</y>
		</point>
		<point>
			<x>106.0</x>
			<y>108.802521008</y>
		</point>
		<point>
			<x>106.79253112</x>
			<y>108.0</y>
		</point>
		<point>
			<x>107.0</x>
			<y>107.795081967</y>
		</point>
		<point>
			<x>107.791836735</x>
			<y>107.0</y>
		</point>
		<point>
			<x>107.8</x>
			<y>106.0</y>
		</point>
		<point>
			<x>107.824324324</x>
			<y>105.0</y>
		</point>
		<point>
			<x>107.799212598</x>
			<y>104.0</y>
		</point>
		<point>
			<x>107.8</x>
			<y>103.0</y>
		</point>
		<point>
			<x>107.779220779</x>
			<y>102.0</y>
		</point>
		<point>
			<x>107.871794872</x>
			<y>101.0</y>
		</point>
		<point>
			<x>107.794354839</x>
			<y>100.0</y>
		</point>
		<point>
			<x>107.825910931</x>
			<y>99.0</y>
		</point>
		<point>
			<x>107.785714286</x>
			<y>98.0</y>
		</point>
		<point>
			<x>107.0</x>
			<y>97.1904761905</y>
		</point>
		<point>
			<x>106.822580645</x>
			<y>97.0</y>
		</point>
		<point>
			<x>106.0</x>
			<y>96.1904761905</y>
		</point>
		<point>
			<x>105.80952381</x>
			<y>96.0</y>
		</point>
		<point>
			<x>105.0</x>
			<y>95.1904761905</y>
		</point>
		<point>
			<x>104.0</x>
			<y>95.1991525424</y>
		</point>
		<point>
			<x>103.805785124</x>
			<y>95.0</y>
		</point>
		<point>
			<x>103.0</x>
			<y>94.1447368421</y>
		</point>
		<point>
			<x>102.848623853</x>
			<y>94.0</y>
		</point>
		<point>
			<x>102.0</x>
			<y>93.1885964912</y>
		</point>
		<point>
			<x>101.0</x>
			<y>93.1837606838</y>
		</point>
		<point>
			<x>100.811403509</x>
			<y>93.0</y>
		</point>
		<point>
			<x>100.0</x>
			<y>92.1474654378</y>
		</point>
		<point>
			<x>99.0</x>
			<y>92.1217391304</y>
		</point>
		<point>
			<x>98.875</x>
			<y>92.0</y>
		</point>
		<point>
			<x>98.0</x>
			<y>91.179916318</y>
		</point>
		<point>
			<x>97.8259109312</x>
			<y>91.0</y>
		</point>
		<point>
			<x>97.0</x>
			<y>90.1673469388</y>
		</point>
		<point>
			<x>96.8225108225</x>
			<y>90.0</y>
		</point>
		<point>
			<x>96.8</x>
			<y>89.0</y>
		</point>
		<point>
			<x>96.7918367347</x>
			<y>88.0</y>
		</point>
		<point>
			<x>97.0</x>
			<y>87.8</y>
		</point>
		<point>
			<x>98.0</x>
			<y>87.8101265823</y>
		</point>
		<point>
			<x>98.7901234568</x>
			<y>87.0</y>
		</point>
		<point>
			<x>99.0</x>
			<y>86.7992125984</y>
		</point>
		<point>
			<x>99.7992125984</x>
			<y>86.0</y>
		</point>
		<point>
			<x>99.7943548387</x>
			<y>85.0</y>
		</point>
		<point>
			<x>100.0</x>
			<y>84.8</y>
		</point>
		<point>
			<x>100.806324111</x>
			<y>84.0</y>
		</point>
		<point>
			<x>101.0</x>
			<y>83.8032128514</y>
		</point>
		<point>
			<x>101.796812749</x>
			<y>83.0</y>
		</point>
		<point>
			<x>101.814345992</x>
			<y>82.0</y>
		</point>
		<point>
			<x>101.773333333</x>
			<y>81.0</y>
		</point>
		<point>
			<x>101.888372093</x>
			<y>80.0</y>
		</point>
		<point>
			<x>101.792682927</x>
			<y>79.0</y>
		</point>
		<point>
			<x>101.87745098</x>
			<y>78.0</y>
		</point>
		<point>
			<x>101.8</x>
			<y>77.0</y>
		</point>
		<point>
			<x>101.0</x>
			<y>76.2</y>
		</point>
		<point>
			<x>100.0</x>
			<y>76.1774193548</y>
		</point>
		<point>
			<x>99.8018018018</x>
			<y>76.0</y>
		</point>
		<point>
			<x>99.85</x>
			<y>75.0</y>
		</point>
		<point>
			<x>99.0</x>
			<y>74.2</y>
		</point>
		<point>
			<x>98.8</x>
			<y>74.0</y>
		</point>
		<point>
			<x>98.0</x>
			<y>73.1936758893</y>
		</point>
		<point>
			<x>97.0</x>
			<y>73.1974248927</y>
		</point>
		<point>
			<x>96.0</x>
			<y>73.2083333333</y>
		</point>
		<point>
			<x>95.0</x>
			<y>73.2</y>
		</point>
		<point>
			<x>94.0</x>
			<y>73.1904761905</y>
		</point>
		<point>
			<x>93.0</x>
			<y>73.1774193548</y>
		</point>
		<point>
			<x>92.0</x>
			<y>73.1976284585</y>
		</point>
		<point>
			<x>91.0</x>
			<y>73.1705069124</y>
		</point>
		<point>
			<x>90.0</x>
			<y>73.2</y>
		</point>
		<point>
			<x>89.0</x>
			<y>73.2</y>
		</point>
		<point>
			<x>88.2</x>
			<y>74.0</y>
		</point>
		<point>
			<x>88.0</x>
			<y>74.2048192771</y>
		</point>
		<point>
			<x>87.0</x>
			<y>74.1312217195</y>
		</point>
		<point>
			<x>86.0</x>
			<y>74.2008368201</y>
		</point>
		<point>
			<x>85.0</x>
			<y>74.1184210526</y>
		</point>
		<point>
			<x>84.0</x>
			<y>74.1638655462</y>
		</point>
		<point>
			<x>83.204</x>
			<y>75.0</y>
		</point>
		<point>
			<x>83.1936758893</x>
			<y>76.0</y>
		</point>
		<point>
			<x>83.0</x>
			<y>76.2</y>
		</point>
		<point>
			<x>82.0</x>
			<y>76.2127659574</y>
		</point>
		<point>
			<x>81.0</x>
			<y>76.1714285714</y>
		</point>
		<point>
			<x>80.0</x>
			<y>76.1955555556</y>
		</point>
		<point>
			<x>79.2130434783</x>
			<y>77.0</y>
		</point>
		<point>
			<x>79.1904761905</x>
			<y>78.0</y>
		</point>
		<point>
			<x>79.2025862069</x>
			<y>79.0</y>
		</point>
		<point>
			<x>79.0</x>
			<y>79.187250996</y>
		</point>
		<point>
			<x>78.1807228916</x>
			<y>80.0</y>
		</point>
		<point>
			<x>78.1528384279</x>
			<y>81.0</y>
		</point>
		<point>
			<x>78.2</x>
			<y>82.0</y>
		</point>
		<point>
			<x>78.231884058</x>
			<y>83.0</y>
		</point>
		<point>
			<x>78.1130434783</x>
			<y>84.0</y>
		</point>
		<point>
			<x>79.0</x>
			<y>84.8</y>
		</point>
		<point>
			<x>79.203187251</x>
			<y>85.0</y>
		</point>
		<point>
			<x>79.1728395062</x>
			<y>86.0</y>
		</point>
		<point>
			<x>79.2023809524</x>
			<y>87.0</y>
		</point>
		<point>
			<x>80.0</x>
			<y>87.7976190476</y>
		</point>
		<point>
			<x>80.204</x>
			<y>88.0</y>
		</point>
		<point>
			<x>81.0</x>
			<y>88.796</y>
		</point>
		<point>
			<x>81.2</x>
			<y>89.0</y>
		</point>
		<point>
			<x>81.1844262295</x>
			<y>90.0</y>
		</point>
		<point>
			<x>82.0</x>
			<y>90.8056680162</y>
		</point>
		<point>
			<x>83.0</x>
			<y>90.8008849558</y>
		</point>
		<point>
			<x>83.1875</x>
			<y>91.0</y>
		</point>
		<point>
			<x>83.1958333333</x>
			<y>92.0</y>
		</point>
		<point>
			<x>83.0</x>
			<y>92.2</y>
		</point>
		<point>
			<x>82.0</x>
			<y>92.1398305085</y>
		</point>
		<point>
			<x>81.1781376518</x>
			<y>93.0</y>
		</point>
		<point>
			<x>81.1762114537</x>
			<y>94.0</y>
		</point>
		<point>
			<x>81.1975806452</x>
			<y>95.0</y>
		</point>
		<point>
			<x>81.1872340426</x>
			<y>96.0</y>
		</point>
		<point>
			<x>81.2</x>
			<y>97.0</y>
		</point>
		<point>
			<x>81.0</x>
			<y>97.2</y>
		</point>
		<point>
			<x>80.1904761905</x>
			<y>98.0</y>
		</point>
		<point>
			<x>80.0</x>
			<y>98.1927710843</y>
		</point>
		<point>
			<x>79.0</x>
			<y>98.2</y>
		</point>
		<point>
			<x>78.8</x>
			<y>98.0</y>
		</point>
		<point>
			<x>78.0</x>
			<y>97.1807228916</y>
		</point>
		<point>
			<x>77.8068669528</x>
			<y>97.0</y>
		</point>
		<point>
			<x>77.0</x>
			<y>96.1255813953</y>
		</point>
		<point>
			<x>76.0</x>
			<y>96.2</y>
		</point>
		<point>
			<x>75.8</x>
			<y>96.0</y>
		</point>
		<point>
			<x>75.0</x>
			<y>95.1807228916</y>
		</point>
		<point>
			<x>74.1904761905</x>
			<y>96.0</y>
		</point>
		<point>
			<x>74.0</x>
			<y>96.1967213115</y>
		</point>
		<point>
			<x>73.0</x>
			<y>96.1888412017</y>
		</point>
		<point>
			<x>72.1710526316</x>
			<y>97.0</y>
		</point>
		<point>
			<x>72.0</x>
			<y>97.1710526316</y>
		</point>
		<point>
			<x>71.0</x>
			<y>97.1869918699</y>
		</point>
		<point>
			<x>70.816</x>
			<y>97.0</y>
		</point>
		<point>
			<x>70.0</x>
			<y>96.2</y>
		</point>
		<point>
			<x>69.8</x>
			<y>96.0</y>
		</point>
		<point>
			<x>69.0</x>
			<y>95.1673469388</y>
		</point>
		<point>
			<x>68.8326530612</x>
			<y>95.0</y>
		</point>
		<point>
			<x>68.8169642857</x>
			<y>94.0</y>
		</point>
		<point>
			<x>68.7984189723</x>
			<y>93.0</y>
		</point>
		<point>
			<x>68.8</x>
			<y>92.0</y>
		</point>
		<point>
			<x>68.85</x>
			<y>91.0</y>
		</point>
		<point>
			<x>68.0</x>
			<y>90.0502793296</y>
		</point>
		<point>
			<x>67.9556650246</x>
			<y>90.0</y>
		</point>
		<point>
			<x>67.7984189723</x>
			<y>89.0</y>
		</point>
		<point>
			<x>67.8685446009</x>
			<y>88.0</y>
		</point>
		<point>
			<x>67.8</x>
			<y>87.0</y>
		</point>
		<point>
			<x>67.88</x>
			<y>86.0</y>
		</point>
		<point>
			<x>67.0</x>
			<y>85.2246696035</y>
		</point>
		<point>
			<x>66.8</x>
			<y>85.0</y>
		</point>
		<point>
			<x>66.0</x>
			<y>84.1968503937</y>
		</point>
		<point>
			<x>65.0</x>
			<y>84.1829787234</y>
		</point>
		<point>
			<x>64.0</x>
			<y>84.1744680851</y>
		</point>
		<point>
			<x>63.0</x>
			<y>84.164556962</y>
		</point>
		<point>
			<x>62.0</x>
			<y>84.2007874016</y>
		</point>
		<point>
			<x>61.1646090535</x>
			<y>85.0</y>
		</point>
		<point>
			<x>61.2</x>
			<y>86.0</y>
		</point>
		<point>
			<x>61.0</x>
			<y>86.203187251</y>
		</point>
		<point>
			<x>60.0</x>
			<y>86.152173913</y>
		</point>
		<point>
			<x>59.1975308642</x>
			<y>87.0</y>
		</point>
		<point>
			<x>59.2056451613</x>
			<y>88.0</y>
		</point>
		<point>
			<x>59.1904761905</x>
			<y>89.0</y>
		</point>
		<point>
			<x>60.0</x>
			<y>89.8225806452</y>
		</point>
		<point>
			<x>60.1774193548</x>
			<y>90.0</y>
		</point>
		<point>
			<x>61.0</x>
			<y>90.8225806452</y>
		</point>
		<point>
			<x>61.1896551724</x>
			<y>91.0</y>
		</point>
		<point>
			<x>61.1216216216</x>
			<y>92.0</y>
		</point>
		<point>
			<x>61.0</x>
			<y>92.1173913043</y>
		</point>
		<point>
			<x>60.1646090535</x>
			<y>93.0</y>
		</point>
		<point>
			<x>60.1506849315</x>
			<y>94.0</y>
		</point>
		<point>
			<x>60.0</x>
			<y>94.1701030928</y>
		</point>
		<point>
			<x>59.2333333333</x>
			<y>95.0</y>
		</point>
		<point>
			<x>59.0</x>
			<y>95.1991869919</y>
		</point>
		<point>
			<x>58.0</x>
			<y>95.0392156863</y>
		</point>
		<point>
			<x>57.9555555556</x>
			<y>95.0</y>
		</point>
		<point>
			<x>57.796812749</x>
			<y>94.0</y>
		</point>
		<point>
			<x>57.8064516129</x>
			<y>93.0</y>
		</point>
		<point>
			<x>57.8091286307</x>
			<y>92.0</y>
		</point>
		<point>
			<x>57.9026548673</x>
			<y>91.0</y>
		</point>
		<point>
			<x>57.8</x>
			<y>90.0</y>
		</point>
		<point>
			<x>57.812244898</x>
			<y>89.0</y>
		</point>
		<point>
			<x>57.8995215311</x>
			<y>88.0</y>
		</point>
		<point>
			<x>57.8356164384</x>
			<y>87.0</y>
		</point>
		<point>
			<x>57.8</x>
			<y>86.0</y>
		</point>
		<point>
			<x>58.0</x>
			<y>85.8</y>
		</point>
		<point>
			<x>58.8395061728</x>
			<y>85.0</y>
		</point>
		<point>
			<x>59.0</x>
			<y>84.8395061728</y>
		</point>
		<point>
			<x>59.8395061728</x>
			<y>84.0</y>
		</point>
		<point>
			<x>59.0</x>
			<y>83.2</y>
		</point>
		<point>
			<x>58.8</x>
			<y>83.0</y>
		</point>
		<point>
			<x>58.8725490196</x>
			<y>82.0</y>
		</point>
		<point>
			<x>58.8008658009</x>
			<y>81.0</y>
		</point>
		<point>
			<x>58.8</x>
			<y>80.0</y>
		</point>
		<point>
			<x>58.0</x>
			<y>79.1604938272</y>
		</point>
		<point>
			<x>57.8361344538</x>
			<y>79.0</y>
		</point>
		<point>
			<x>57.8</x>
			<y>78.0</y>
		</point>
		<point>
			<x>57.0</x>
			<y>77.2</y>
		</point>
		<point>
			<x>56.7792207792</x>
			<y>77.0</y>
		</point>
		<point>
			<x>56.0</x>
			<y>76.2070484581</y>
		</point>
		<point>
			<x>55.0</x>
			<y>76.2015810277</y>
		</point>
		<point>
			<x>54.0</x>
			<y>76.2</y>
		</point>
		<point>
			<x>53.0</x>
			<y>76.2085106383</y>
		</point>
		<point>
			<x>52.0</x>
			<y>76.2</y>
		</point>
		<point>
			<x>51.184</x>
			<y>77.0</y>
		</point>
		<point>
			<x>51.0</x>
			<y>77.1932773109</y>
		</point>
		<point>
			<x>50.1028037383</x>
			<y>78.0</y>
		</point>
		<point>
			<x>50.204</x>
			<y>79.0</y>
		</point>
		<point>
			<x>50.1707317073</x>
			<y>80.0</y>
		</point>
		<point>
			<x>50.0</x>
			<y>80.2068965517</y>
		</point>
		<point>
			<x>49.1436170213</x>
			<y>81.0</y>
		</point>
		<point>
			<x>49.1936758893</x>
			<y>82.0</y>
		</point>
		<point>
			<x>49.2133891213</x>
			<y>83.0</y>
		</point>
		<point>
			<x>49.192139738</x>
			<y>84.0</y>
		</point>
		<point>
			<x>49.204</x>
			<y>85.0</y>
		</point>
		<point>
			<x>49.1904761905</x>
			<y>86.0</y>
		</point>
		<point>
			<x>49.1626794258</x>
			<y>87.0</y>
		</point>
		<point>
			<x>49.204</x>
			<y>88.0</y>
		</point>
		<point>
			<x>49.0</x>
			<y>88.2064777328</y>
		</point>
		<point>
			<x>48.1694915254</x>
			<y>89.0</y>
		</point>
		<point>
			<x>48.2</x>
			<y>90.0</y>
		</point>
		<point>
			<x>48.1913875598</x>
			<y>91.0</y>
		</point>
		<point>
			<x>48.1936758893</x>
			<y>92.0</y>
		</point>
		<point>
			<x>48.2</x>
			<y>93.0</y>
		</point>
		<point>
			<x>48.1255813953</x>
			<y>94.0</y>
		</point>
		<point>
			<x>48.2056451613</x>
			<y>95.0</y>
		</point>
		<point>
			<x>48.1943319838</x>
			<y>96.0</y>
		</point>
		<point>
			<x>48.1918367347</x>
			<y>97.0</y>
		</point>
		<point>
			<x>48.2023809524</x>
			<y>98.0</y>
		</point>
		<point>
			<x>48.1673469388</x>
			<y>99.0</y>
		</point>
		<point>
			<x>48.220657277</x>
			<y>100.0</y>
		</point>
		<point>
			<x>48.0</x>
			<y>100.187250996</y>
		</point>
		<point>
			<x>47.1904761905</x>
			<y>101.0</y>
		</point>
		<point>
			<x>47.2062780269</x>
			<y>102.0</y>
		</point>
		<point>
			<x>47.1807228916</x>
			<y>103.0</y>
		</point>
		<point>
			<x>47.188034188</x>
			<y>104.0</y>
		</point>
		<point>
			<x>48.0</x>
			<y>104.788381743</y>
		</point>
		<point>
			<x>48.2</x>
			<y>105.0</y>
		</point>
		<point>
			<x>49.0</x>
			<y>105.8</y>
		</point>
		<point>
			<x>49.2</x>
			<y>106.0</y>
		</point>
		<point>
			<x>50.0</x>
			<y>106.8</y>
		</point>
		<point>
			<x>51.0</x>
			<y>106.846473029</y>
		</point>
		<point>
			<x>52.0</x>
			<y>106.793522267</y>
		</point>
		<point>
			<x>53.0</x>
			<y>106.766666667</y>
		</point>
		<point>
			<x>54.0</x>
			<y>106.886255924</y>
		</point>
		<point>
			<x>55.0</x>
			<y>106.791489362</y>
		</point>
		<point>
			<x>56.0</x>
			<y>106.799212598</y>
		</point>
		<point>
			<x>56.8185483871</x>
			<y>106.0</y>
		</point>
		<point>
			<x>57.0</x>
			<y>105.819277108</y>
		</point>
		<point>
			<x>58.0</x>
			<y>105.793522267</y>
		</point>
		<point>
			<x>59.0</x>
			<y>105.836909871</y>
		</point>
		<point>
			<x>60.0</x>
			<y>105.791666667</y>
		</point>
		<point>
			<x>60.2202643172</x>
			<y>106.0</y>
		</point>
		<point>
			<x>60.1452991453</x>
			<y>107.0</y>
		</point>
		<point>
			<x>60.2015810277</x>
			<y>108.0</y>
		</point>
		<point>
			<x>60.2016460905</x>
			<y>109.0</y>
		</point>
		<point>
			<x>60.1525423729</x>
			<y>110.0</y>
		</point>
		<point>
			<x>60.2056451613</x>
			<y>111.0</y>
		</point>
		<point>
			<x>61.0</x>
			<y>111.845493562</y>
		</point>
		<point>
			<x>61.1551724138</x>
			<y>112.0</y>
		</point>
		<point>
			<x>61.2023809524</x>
			<y>113.0</y>
		</point>
		<point>
			<x>62.0</x>
			<y>113.827160494</y>
		</point>
		<point>
			<x>62.1953488372</x>
			<y>114.0</y>
		</point>
		<point>
			<x>63.0</x>
			<y>114.835748792</y>
		</point>
		<point>
			<x>64.0</x>
			<y>114.808333333</y>
		</point>
		<point>
			<x>64.184</x>
			<y>115.0</y>
		</point>
		<point>
			<x>65.0</x>
			<y>115.8</y>
		</point>
		<point>
			<x>66.0</x>
			<y>115.870967742</y>
		</point>
		<point>
			<x>67.0</x>
			<y>115.791836735</y>
		</point>
		<point>
			<x>67.2098765432</x>
			<y>116.0</y>
		</point>
		<point>
			<x>68.0</x>
			<y>116.838427948</y>
		</point>
		<point>
			<x>69.0</x>
			<y>116.8</y>
		</point>
		<point>
			<x>69.8</x>
			<y>116.0</y>
		</point>
	</contour>
	<contour>
		<point>
			<x>99.0</x>
			<y>104.160869565</y>
		</point>
		<point>
			<x>98.0</x>
			<y>104.2</y>
		</point>
		<point>
			<x>97.0</x>
			<y>104.190283401</y>
		</point>
		<point>
			<x>96.0</x>
			<y>104.197530864</y>
		</point>
		<point>
			<x>95.0</x>
			<y>104.175732218</y>
		</point>
		<point>
			<x>94.0</x>
			<y>104.204</y>
		</point>
		<point>
			<x>93.0</x>
			<y>104.192771084</y>
		</point>
		<point>
			<x>92.0</x>
			<y>104.184</y>
		</point>
		<point>
			<x>91.8091286307</x>
			<y>104.0</y>
		</point>
		<point>
			<x>91.8232758621</x>
			<y>103.0</y>
		</point>
		<point>
			<x>91.0</x>
			<y>102.162280702</y>
		</point>
		<point>
			<x>90.8438818565</x>
			<y>102.0</y>
		</point>
		<point>
			<x>90.7909836066</x>
			<y>101.0</y>
		</point>
		<point>
			<x>90.0</x>
			<y>100.209016393</y>
		</point>
		<point>
			<x>89.7943548387</x>
			<y>100.0</y>
		</point>
		<point>
			<x>89.8023715415</x>
			<y>99.0</y>
		</point>
		<point>
			<x>90.0</x>
			<y>98.8023715415</y>
		</point>
		<point>
			<x>90.7992125984</x>
			<y>98.0</y>
		</point>
		<point>
			<x>91.0</x>
			<y>97.8</y>
		</point>
		<point>
			<x>91.8</x>
			<y>97.0</y>
		</point>
		<point>
			<x>92.0</x>
			<y>96.8</y>
		</point>
		<point>
			<x>93.0</x>
			<y>96.8242677824</y>
		</point>
		<point>
			<x>94.0</x>
			<y>96.7866108787</y>
		</point>
		<point>
			<x>94.2</x>
			<y>97.0</y>
		</point>
		<point>
			<x>95.0</x>
			<y>97.8</y>
		</point>
		<point>
			<x>96.0</x>
			<y>97.8097165992</y>
		</point>
		<point>
			<x>97.0</x>
			<y>97.7926829268</y>
		</point>
		<point>
			<x>97.2081632653</x>
			<y>98.0</y>
		</point>
		<point>
			<x>98.0</x>
			<y>98.8255319149</y>
		</point>
		<point>
			<x>99.0</x>
			<y>98.8564814815</y>
		</point>
		<point>
			<x>99.1359649123</x>
			<y>99.0</y>
		</point>
		<point>
			<x>100.0</x>
			<y>99.7943548387</y>
		</point>
		<point>
			<x>100.214285714</x>
			<y>100.0</y>
		</point>
		<point>
			<x>100.116883117</x>
			<y>101.0</y>
		</point>
		<point>
			<x>100.202380952</x>
			<y>102.0</y>
		</point>
		<point>
			<x>100.0</x>
			<y>102.2</y>
		</point>
		<point>
			<x>99.2</x>
			<y>103.0</y>
		</point>
		<point>
			<x>99.1622807018</x>
			<y>104.0</y>
		</point>
		<point>
			<x>99.0</x>
			<y>104.160869565</y>
		</point>
	</contour>
	<contour>
		<point>
			<x>205.829166667</x>
			<y>312.0</y>
		</point>
		<point>
			<x>206.0</x>
			<y>311.832653061</y>
		</point>
		<point>
			<x>207.0</x>
			<y>311.798418972</y>
		</point>
		<point>
			<x>208.0</x>
			<y>311.796</y>
		</point>
		<point>
			<x>209.0</x>
			<y>311.8</y>
		</point>
		<point>
			<x>209.796812749</x>
			<y>311.0</y>
		</point>
		<point>
			<x>210.0</x>
			<y>310.789256198</y>
		</point>
		<point>
			<x>211.0</x>
			<y>310.808695652</y>
		</point>
		<point>
			<x>211.784810127</x>
			<y>310.0</y>
		</point>
		<point>
			<x>211.80952381</x>
			<y>309.0</y>
		</point>
		<point>
			<x>211.794354839</x>
			<y>308.0</y>
		</point>
		<point>
			<x>212.0</x>
			<y>307.8</y>
		</point>
		<point>
			<x>212.8</x>
			<y>307.0</y>
		</point>
		<point>
			<x>213.0</x>
			<y>306.8</y>
		</point>
		<point>
			<x>214.0</x>
			<y>306.853556485</y>
		</point>
		<point>
			<x>215.0</x>
			<y>306.794979079</y>
		</point>
		<point>
			<x>216.0</x>
			<y>306.83255814</y>
		</point>
		<point>
			<x>216.828703704</x>
			<y>306.0</y>
		</point>
		<point>
			<x>216.839506173</x>
			<y>305.0</y>
		</point>
		<point>
			<x>217.0</x>
			<y>304.8375</y>
		</point>
		<point>
			<x>218.0</x>
			<y>304.795180723</y>
		</point>
		<point>
			<x>219.0</x>
			<y>304.812749004</y>
		</point>
		<point>
			<x>219.80952381</x>
			<y>304.0</y>
		</point>
		<point>
			<x>220.0</x>
			<y>303.795744681</y>
		</point>
		<point>
			<x>220.80952381</x>
			<y>303.0</y>
		</point>
		<point>
			<x>221.0</x>
			<y>302.794392523</y>
		</point>
		<point>
			<x>222.0</x>
			<y>302.886956522</y>
		</point>
		<point>
			<x>223.0</x>
			<y>302.8</y>
		</point>
		<point>
			<x>224.0</x>
			<y>302.795180723</y>
		</point>
		<point>
			<x>224.795180723</x>
			<y>302.0</y>
		</point>
		<point>
			<x>225.0</x>
			<y>301.782051282</y>
		</point>
		<point>
			<x>226.0</x>
			<y>301.871111111</y>
		</point>
		<point>
			<x>226.852173913</x>
			<y>301.0</y>
		</point>
		<point>
			<x>227.0</x>
			<y>300.842592593</y>
		</point>
		<point>
			<x>227.838709677</x>
			<y>300.0</y>
		</point>
		<point>
			<x>228.0</x>
			<y>299.83490566</y>
		</point>
		<point>
			<x>229.0</x>
			<y>299.842975207</y>
		</point>
		<point>
			<x>229.8</x>
			<y>299.0</y>
		</point>
		<point>
			<x>230.0</x>
			<y>298.796</y>
		</point>
		<point>
			<x>230.796</x>
			<y>298.0</y>
		</point>
		<point>
			<x>231.0</x>
			<y>297.795180723</y>
		</point>
		<point>
			<x>232.0</x>
			<y>297.891509434</y>
		</point>
		<point>
			<x>232.7875</x>
			<y>297.0</y>
		</point>
		<point>
			<x>233.0</x>
			<y>296.8</y>
		</point>
		<point>
			<x>233.8</x>
			<y>296.0</y>
		</point>
		<point>
			<x>234.0</x>
			<y>295.8</y>
		</point>
		<point>
			<x>234.8</x>
			<y>295.0</y>
		</point>
		<point>
			<x>235.0</x>
			<y>294.8</y>
		</point>
		<point>
			<x>235.842975207</x>
			<y>294.0</y>
		</point>
		<point>
			<x>235.776315789</x>
			<y>293.0</y>
		</point>
		<point>
			<x>235.842975207</x>
			<y>292.0</y>
		</point>
		<point>
			<x>235.0</x>
			<y>291.2</y>
		</point>
		<point>
			<x>234.798418972</x>
			<y>291.0</y>
		</point>
		<point>
			<x>234.0</x>
			<y>290.18875502</y>
		</point>
		<point>
			<x>233.812</x>
			<y>290.0</y>
		</point>
		<point>
			<x>233.0</x>
			<y>289.154166667</y>
		</point>
		<point>
			<x>232.841880342</x>
			<y>289.0</y>
		</point>
		<point>
			<x>232.0</x>
			<y>288.182572614</y>
		</point>
		<point>
			<x>231.819672131</x>
			<y>288.0</y>
		</point>
		<point>
			<x>231.0</x>
			<y>287.056603774</y>
		</point>
		<point>
			<x>230.937823834</x>
			<y>287.0</y>
		</point>
		<point>
			<x>230.0</x>
			<y>286.099502488</y>
		</point>
		<point>
			<x>229.0</x>
			<y>286.209876543</y>
		</point>
		<point>
			<x>228.0</x>
			<y>286.204819277</y>
		</point>
		<point>
			<x>227.8</x>
			<y>286.0</y>
		</point>
		<point>
			<x>227.812244898</x>
			<y>285.0</y>
		</point>
		<point>
			<x>227.0</x>
			<y>284.187755102</y>
		</point>
		<point>
			<x>226.0</x>
			<y>284.16872428</y>
		</point>
		<point>
			<x>225.0</x>
			<y>284.209016393</y>
		</point>
		<point>
			<x>224.0</x>
			<y>284.184</y>
		</point>
		<point>
			<x>223.0</x>
			<y>284.184</y>
		</point>
		<point>
			<x>222.0</x>
			<y>284.219827586</y>
		</point>
		<point>
			<x>221.169724771</x>
			<y>285.0</y>
		</point>
		<point>
			<x>221.0</x>
			<y>285.180487805</y>
		</point>
		<point>
			<x>220.0</x>
			<y>285.160493827</y>
		</point>
		<point>
			<x>219.834042553</x>
			<y>285.0</y>
		</point>
		<point>
			<x>219.0</x>
			<y>284.203252033</y>
		</point>
		<point>
			<x>218.803149606</x>
			<y>284.0</y>
		</point>
		<point>
			<x>218.824034335</x>
			<y>283.0</y>
		</point>
		<point>
			<x>218.0</x>
			<y>282.203319502</y>
		</point>
		<point>
			<x>217.119266055</x>
			<y>283.0</y>
		</point>
		<point>
			<x>217.0</x>
			<y>283.123222749</y>
		</point>
		<point>
			<x>216.0</x>
			<y>283.2</y>
		</point>
		<point>
			<x>215.2</x>
			<y>284.0</y>
		</point>
		<point>
			<x>215.0</x>
			<y>284.21888412</y>
		</point>
		<point>
			<x>214.0</x>
			<y>284.142857143</y>
		</point>
		<point>
			<x>213.0</x>
			<y>284.2</y>
		</point>
		<point>
			<x>212.0</x>
			<y>284.2</y>
		</point>
		<point>
			<x>211.8</x>
			<y>284.0</y>
		</point>
		<point>
			<x>211.807531381</x>
			<y>283.0</y>
		</point>
		<point>
			<x>212.0</x>
			<y>282.815261044</y>
		</point>
		<point>
			<x>213.0</x>
			<y>282.8</y>
		</point>
		<point>
			<x>214.0</x>
			<y>282.796812749</y>
		</point>
		<point>
			<x>214.819672131</x>
			<y>282.0</y>
		</point>
		<point>
			<x>215.0</x>
			<y>281.816666667</y>
		</point>
		<point>
			<x>216.0</x>
			<y>281.834024896</y>
		</point>
		<point>
			<x>216.813765182</x>
			<y>281.0</y>
		</point>
		<point>
			<x>216.0</x>
			<y>280.199203187</y>
		</point>
		<point>
			<x>215.0</x>
			<y>280.183333333</y>
		</point>
		<point>
			<x>214.813559322</x>
			<y>280.0</y>
		</point>
		<point>
			<x>214.0</x>
			<y>279.182978723</y>
		</point>
		<point>
			<x>213.0</x>
			<y>279.184</y>
		</point>
		<point>
			<x>212.0</x>
			<y>279.204</y>
		</point>
		<point>
			<x>211.8</x>
			<y>279.0</y>
		</point>
		<point>
			<x>211.872037915</x>
			<y>278.0</y>
		</point>
		<point>
			<x>211.0</x>
			<y>277.217021277</y>
		</point>
		<point>
			<x>210.0</x>
			<y>277.2</y>
		</point>
		<point>
			<x>209.0</x>
			<y>277.2</y>
		</point>
		<point>
			<x>208.0</x>
			<y>277.201612903</y>
		</point>
		<point>
			<x>207.0</x>
			<y>277.206477733</y>
		</point>
		<point>
			<x>206.0</x>
			<y>277.196850394</y>
		</point>
		<point>
			<x>205.0</x>
			<y>277.2</y>
		</point>
		<point>
			<x>204.0</x>
			<y>277.185344828</y>
		</point>
		<point>
			<x>203.152466368</x>
			<y>278.0</y>
		</point>
		<point>
			<x>203.2</x>
			<y>279.0</y>
		</point>
		<point>
			<x>203.0</x>
			<y>279.205645161</y>
		</point>
		<point>
			<x>202.205645161</x>
			<y>280.0</y>
		</point>
		<point>
			<x>202.0</x>
			<y>280.201581028</y>
		</point>
		<point>
			<x>201.201581028</x>
			<y>281.0</y>
		</point>
		<point>
			<x>201.196787149</x>
			<y>282.0</y>
		</point>
		<point>
			<x>201.147679325</x>
			<y>283.0</y>
		</point>
		<point>
			<x>201.0</x>
			<y>283.147679325</y>
		</point>
		<point>
			<x>200.192</x>
			<y>284.0</y>
		</point>
		<point>
			<x>201.0</x>
			<y>284.798418972</y>
		</point>
		<point>
			<x>202.0</x>
			<y>284.926315789</y>
		</point>
		<point>
			<x>202.065116279</x>
			<y>285.0</y>
		</point>
		<point>
			<x>203.0</x>
			<y>285.8375</y>
		</point>
		<point>
			<x>203.160493827</x>
			<y>286.0</y>
		</point>
		<point>
			<x>203.210743802</x>
			<y>287.0</y>
		</point>
		<point>
			<x>204.0</x>
			<y>287.795833333</y>
		</point>
		<point>
			<x>205.0</x>
			<y>287.871794872</y>
		</point>
		<point>
			<x>205.130434783</x>
			<y>288.0</y>
		</point>
		<point>
			<x>205.0</x>
			<y>288.132743363</y>
		</point>
		<point>
			<x>204.0</x>
			<y>288.198380567</y>
		</point>
		<point>
			<x>203.123893805</x>
			<y>289.0</y>
		</point>
		<point>
			<x>203.0</x>
			<y>289.130232558</y>
		</point>
		<point>
			<x>202.0</x>
			<y>289.2</y>
		</point>
		<point>
			<x>201.0</x>
			<y>289.092592593</y>
		</point>
		<point>
			<x>200.0</x>
			<y>289.211453744</y>
		</point>
		<point>
			<x>199.0</x>
			<y>289.210970464</y>
		</point>
		<point>
			<x>198.0</x>
			<y>289.197580645</y>
		</point>
		<point>
			<x>197.0</x>
			<y>289.153526971</y>
		</point>
		<point>
			<x>196.0</x>
			<y>289.208163265</y>
		</point>
		<point>
			<x>195.0</x>
			<y>289.207317073</y>
		</point>
		<point>
			<x>194.0</x>
			<y>289.142857143</y>
		</point>
		<point>
			<x>193.0</x>
			<y>289.19047619</y>
		</point>
		<point>
			<x>192.0</x>
			<y>289.206477733</y>
		</point>
		<point>
			<x>191.0</x>
			<y>289.191919192</y>
		</point>
		<point>
			<x>190.0</x>
			<y>289.200787402</y>
		</point>
		<point>
			<x>189.0</x>
			<y>289.174089069</y>
		</point>
		<point>
			<x>188.146443515</x>
			<y>290.0</y>
		</point>
		<point>
			<x>188.0</x>
			<y>290.148305085</y>
		</point>
		<point>
			<x>187.0</x>
			<y>290.2</y>
		</point>
		<point>
			<x>186.0</x>
			<y>290.2</y>
		</point>
		<point>
			<x>185.0</x>
			<y>290.101851852</y>
		</point>
		<point>
			<x>184.0</x>
			<y>290.201581028</y>
		</point>
		<point>
			<x>183.0</x>
			<y>290.201581028</y>
		</point>
		<point>
			<x>182.0</x>
			<y>290.201581028</y>
		</point>
		<point>
			<x>181.0</x>
			<y>290.201581028</y>
		</point>
		<point>
			<x>180.0</x>
			<y>290.200787402</y>
		</point>
		<point>
			<x>179.0</x>
			<y>290.200787402</y>
		</point>
		<point>
			<x>178.0</x>
			<y>290.200787402</y>
		</point>
		<point>
			<x>177.0</x>
			<y>290.200787402</y>
		</point>
		<point>
			<x>176.0</x>
			<y>290.2</y>
		</point>
		<point>
			<x>175.0</x>
			<y>290.204918033</y>
		</point>
		<point>
			<x>174.0</x>
			<y>290.193675889</y>
		</point>
		<point>
			<x>173.0</x>
			<y>290.217948718</y>
		</point>
		<point>
			<x>172.0</x>
			<y>290.2</y>
		</point>
		<point>
			<x>171.2</x>
			<y>291.0</y>
		</point>
		<point>
			<x>171.0</x>
			<y>291.2</y>
		</point>
		<point>
			<x>170.0</x>
			<y>291.137614679</y>
		</point>
		<point>
			<x>169.0</x>
			<y>291.216101695</y>
		</point>
		<point>
			<x>168.0</x>
			<y>291.170731707</y>
		</point>
		<point>
			<x>167.0</x>
			<y>291.198347107</y>
		</point>
		<point>
			<x>166.0</x>
			<y>291.148305085</y>
		</point>
		<point>
			<x>165.0</x>
			<y>291.196261682</y>
		</point>
		<point>
			<x>164.0</x>
			<y>291.203187251</y>
		</point>
		<point>
			<x>163.203187251</x>
			<y>292.0</y>
		</point>
		<point>
			<x>163.0</x>
			<y>292.204819277</y>
		</point>
		<point>
			<x>162.0</x>
			<y>292.126126126</y>
		</point>
		<point>
			<x>161.0</x>
			<y>292.206477733</y>
		</point>
		<point>
			<x>160.0</x>
			<y>292.196850394</y>
		</point>
		<point>
			<x>159.0</x>
			<y>292.202380952</y>
		</point>
		<point>
			<x>158.0</x>
			<y>292.202380952</y>
		</point>
		<point>
			<x>157.0</x>
			<y>292.202380952</y>
		</point>
		<point>
			<x>156.0</x>
			<y>292.202380952</y>
		</point>
		<point>
			<x>155.0</x>
			<y>292.202380952</y>
		</point>
		<point>
			<x>154.0</x>
			<y>292.202380952</y>
		</point>
		<point>
			<x>153.0</x>
			<y>292.202380952</y>
		</point>
		<point>
			<x>152.0</x>
			<y>292.202380952</y>
		</point>
		<point>
			<x>151.0</x>
			<y>292.202380952</y>
		</point>
		<point>
			<x>150.0</x>
			<y>292.202380952</y>
		</point>
		<point>
			<x>149.0</x>
			<y>292.202380952</y>
		</point>
		<point>
			<x>148.0</x>
			<y>292.202380952</y>
		</point>
		<point>
			<x>147.0</x>
			<y>292.202380952</y>
		</point>
		<point>
			<x>146.0</x>
			<y>292.202380952</y>
		</point>
		<point>
			<x>145.0</x>
			<y>292.202380952</y>
		</point>
		<point>
			<x>144.0</x>
			<y>292.202380952</y>
		</point>
		<point>
			<x>143.0</x>
			<y>292.2</y>
		</point>
		<point>
			<x>142.0</x>
			<y>292.17826087</y>
		</point>
		<point>
			<x>141.0</x>
			<y>292.2</y>
		</point>
		<point>
			<x>140.0</x>
			<y>292.168421053</y>
		</point>
		<point>
			<x>139.0</x>
			<y>292.2</y>
		</point>
		<point>
			<x>138.0</x>
			<y>292.2</y>
		</point>
		<point>
			<x>137.2</x>
			<y>293.0</y>
		</point>
		<point>
			<x>137.0</x>
			<y>293.202380952</y>
		</point>
		<point>
			<x>136.0</x>
			<y>293.125581395</y>
		</point>
		<point>
			<x>135.153153153</x>
			<y>294.0</y>
		</point>
		<point>
			<x>135.0</x>
			<y>294.149779736</y>
		</point>
		<point>
			<x>134.175213675</x>
			<y>295.0</y>
		</point>
		<point>
			<x>134.2</x>
			<y>296.0</y>
		</point>
		<point>
			<x>134.211618257</x>
			<y>297.0</y>
		</point>
		<point>
			<x>134.025641026</x>
			<y>298.0</y>
		</point>
		<point>
			<x>135.0</x>
			<y>298.837004405</y>
		</point>
		<point>
			<x>135.156779661</x>
			<y>299.0</y>
		</point>
		<point>
			<x>135.18875502</x>
			<y>300.0</y>
		</point>
		<point>
			<x>136.0</x>
			<y>300.798418972</y>
		</point>
		<point>
			<x>137.0</x>
			<y>300.798418972</y>
		</point>
		<point>
			<x>138.0</x>
			<y>300.798418972</y>
		</point>
		<point>
			<x>139.0</x>
			<y>300.799212598</y>
		</point>
		<point>
			<x>140.0</x>
			<y>300.799212598</y>
		</point>
		<point>
			<x>141.0</x>
			<y>300.799212598</y>
		</point>
		<point>
			<x>142.0</x>
			<y>300.799212598</y>
		</point>
		<point>
			<x>143.0</x>
			<y>300.799212598</y>
		</point>
		<point>
			<x>144.0</x>
			<y>300.8</y>
		</point>
		<point>
			<x>144.803149606</x>
			<y>300.0</y>
		</point>
		<point>
			<x>145.0</x>
			<y>299.784482759</y>
		</point>
		<point>
			<x>146.0</x>
			<y>299.822580645</y>
		</point>
		<point>
			<x>147.0</x>
			<y>299.782051282</y>
		</point>
		<point>
			<x>147.782051282</x>
			<y>299.0</y>
		</point>
		<point>
			<x>148.0</x>
			<y>298.796812749</y>
		</point>
		<point>
			<x>149.0</x>
			<y>298.889400922</y>
		</point>
		<point>
			<x>150.0</x>
			<y>298.796</y>
		</point>
		<point>
			<x>151.0</x>
			<y>298.836820084</y>
		</point>
		<point>
			<x>152.0</x>
			<y>298.796</y>
		</point>
		<point>
			<x>153.0</x>
			<y>298.796</y>
		</point>
		<point>
			<x>154.0</x>
			<y>298.796</y>
		</point>
		<point>
			<x>155.0</x>
			<y>298.796</y>
		</point>
		<point>
			<x>156.0</x>
			<y>298.796</y>
		</point>
		<point>
			<x>157.0</x>
			<y>298.796</y>
		</point>
		<point>
			<x>158.0</x>
			<y>298.796</y>
		</point>
		<point>
			<x>159.0</x>
			<y>298.796</y>
		</point>
		<point>
			<x>160.0</x>
			<y>298.8</y>
		</point>
		<point>
			<x>161.0</x>
			<y>298.8</y>
		</point>
		<point>
			<x>162.0</x>
			<y>298.817021277</y>
		</point>
		<point>
			<x>163.0</x>
			<y>298.8</y>
		</point>
		<point>
			<x>163.8</x>
			<y>298.0</y>
		</point>
		<point>
			<x>164.0</x>
			<y>297.8</y>
		</point>
		<point>
			<x>165.0</x>
			<y>297.856540084</y>
		</point>
		<point>
			<x>166.0</x>
			<y>297.791836735</y>
		</point>
		<point>
			<x>167.0</x>
			<y>297.8</y>
		</point>
		<point>
			<x>168.0</x>
			<y>297.793522267</y>
		</point>
		<point>
			<x>169.0</x>
			<y>297.799196787</y>
		</point>
		<point>
			<x>170.0</x>
			<y>297.8</y>
		</point>
		<point>
			<x>171.0</x>
			<y>297.818548387</y>
		</point>
		<point>
			<x>171.200892857</x>
			<y>298.0</y>
		</point>
		<point>
			<x>172.0</x>
			<y>298.806306306</y>
		</point>
		<point>
			<x>173.0</x>
			<y>298.813278008</y>
		</point>
		<point>
			<x>173.793522267</x>
			<y>298.0</y>
		</point>
		<point>
			<x>174.0</x>
			<y>297.796</y>
		</point>
		<point>
			<x>175.0</x>
			<y>297.8</y>
		</point>
		<point>
			<x>176.0</x>
			<y>297.830508475</y>
		</point>
		<point>
			<x>177.0</x>
			<y>297.832618026</y>
		</point>
		<point>
			<x>178.0</x>
			<y>297.832618026</y>
		</point>
		<point>
			<x>179.0</x>
			<y>297.825531915</y>
		</point>
		<point>
			<x>180.0</x>
			<y>297.819327731</y>
		</point>
		<point>
			<x>181.0</x>
			<y>297.813278008</y>
		</point>
		<point>
			<x>182.0</x>
			<y>297.815899582</y>
		</point>
		<point>
			<x>183.0</x>
			<y>297.81512605</y>
		</point>
		<point>
			<x>184.0</x>
			<y>297.808333333</y>
		</point>
		<point>
			<x>185.0</x>
			<y>297.8125</y>
		</point>
		<point>
			<x>186.0</x>
			<y>297.815899582</y>
		</point>
		<point>
			<x>187.0</x>
			<y>297.82278481</y>
		</point>
		<point>
			<x>188.0</x>
			<y>297.822033898</y>
		</point>
		<point>
			<x>189.0</x>
			<y>297.824786325</y>
		</point>
		<point>
			<x>190.0</x>
			<y>297.824034335</y>
		</point>
		<point>
			<x>191.0</x>
			<y>297.820512821</y>
		</point>
		<point>
			<x>192.0</x>
			<y>297.808</y>
		</point>
		<point>
			<x>193.0</x>
			<y>297.8</y>
		</point>
		<point>
			<x>193.806324111</x>
			<y>297.0</y>
		</point>
		<point>
			<x>194.0</x>
			<y>296.801619433</y>
		</point>
		<point>
			<x>195.0</x>
			<y>296.8</y>
		</point>
		<point>
			<x>196.0</x>
			<y>296.8</y>
		</point>
		<point>
			<x>197.0</x>
			<y>296.796747967</y>
		</point>
		<point>
			<x>197.196850394</x>
			<y>297.0</y>
		</point>
		<point>
			<x>198.0</x>
			<y>297.803149606</y>
		</point>
		<point>
			<x>199.0</x>
			<y>297.80876494</y>
		</point>
		<point>
			<x>200.0</x>
			<y>297.865116279</y>
		</point>
		<point>
			<x>201.0</x>
			<y>297.796</y>
		</point>
		<point>
			<x>202.0</x>
			<y>297.800829876</y>
		</point>
		<point>
			<x>203.0</x>
			<y>297.917050691</y>
		</point>
		<point>
			<x>203.802419355</x>
			<y>297.0</y>
		</point>
		<point>
			<x>204.0</x>
			<y>296.806324111</y>
		</point>
		<point>
			<x>205.0</x>
			<y>296.8</y>
		</point>
		<point>
			<x>206.0</x>
			<y>296.866359447</y>
		</point>
		<point>
			<x>207.0</x>
			<y>296.798418972</y>
		</point>
		<point>
			<x>208.0</x>
			<y>296.798418972</y>
		</point>
		<point>
			<x>209.0</x>
			<y>296.796812749</y>
		</point>
		<point>
			<x>210.0</x>
			<y>296.808</y>
		</point>
		<point>
			<x>211.0</x>
			<y>296.790983607</y>
		</point>
		<point>
			<x>211.2</x>
			<y>297.0</y>
		</point>
		<point>
			<x>211.200787402</x>
			<y>298.0</y>
		</point>
		<point>
			<x>211.182978723</x>
			<y>299.0</y>
		</point>
		<point>
			<x>211.176470588</x>
			<y>300.0</y>
		</point>
		<point>
			<x>211.0</x>
			<y>300.189189189</y>
		</point>
		<point>
			<x>210.0</x>
			<y>300.17768595</y>
		</point>
		<point>
			<x>209.0</x>
			<y>300.204</y>
		</point>
		<point>
			<x>208.0</x>
			<y>300.2</y>
		</point>
		<point>
			<x>207.0</x>
			<y>300.191489362</y>
		</point>
		<point>
			<x>206.0</x>
			<y>300.131818182</y>
		</point>
		<point>
			<x>205.0</x>
			<y>300.196850394</y>
		</point>
		<point>
			<x>204.0</x>
			<y>300.2</y>
		</point>
		<point>
			<x>203.0</x>
			<y>300.2</y>
		</point>
		<point>
			<x>202.0</x>
			<y>300.162162162</y>
		</point>
		<point>
			<x>201.17699115</x>
			<y>301.0</y>
		</point>
		<point>
			<x>201.201612903</x>
			<y>302.0</y>
		</point>
		<point>
			<x>201.0</x>
			<y>302.201612903</y>
		</point>
		<point>
			<x>200.204819277</x>
			<y>303.0</y>
		</point>
		<point>
			<x>200.205020921</x>
			<y>304.0</y>
		</point>
		<point>
			<x>200.0</x>
			<y>304.193675889</y>
		</point>
		<point>
			<x>199.2</x>
			<y>305.0</y>
		</point>
		<point>
			<x>199.2</x>
			<y>306.0</y>
		</point>
		<point>
			<x>199.175732218</x>
			<y>307.0</y>
		</point>
		<point>
			<x>199.168776371</x>
			<y>308.0</y>
		</point>
		<point>
			<x>199.19047619</x>
			<y>309.0</y>
		</point>
		<point>
			<x>199.187250996</x>
			<y>310.0</y>
		</point>
		<point>
			<x>200.0</x>
			<y>310.80952381</y>
		</point>
		<point>
			<x>200.202531646</x>
			<y>311.0</y>
		</point>
		<point>
			<x>201.0</x>
			<y>311.82173913</y>
		</point>
		<point>
			<x>202.0</x>
			<y>311.803149606</y>
		</point>
		<point>
			<x>203.0</x>
			<y>311.895734597</y>
		</point>
		<point>
			<x>203.105769231</x>
			<y>312.0</y>
		</point>
		<point>
			<x>204.0</x>
			<y>312.801724138</y>
		</point>
		<point>
			<x>205.0</x>
			<y>312.85042735</y>
		</point>
		<point>
			<x>205.829166667</x>
			<y>312.0</y>
		</point>
	</contour>
	<contour>
		<point>
			<x>76.8669724771</x>
			<y>316.0</y>
		</point>
		<point>
			<x>77.0</x>
			<y>315.869369369</y>
		</point>
		<point>
			<x>78.0</x>
			<y>315.8</y>
		</point>
		<point>
			<x>78.8395061728</x>
			<y>315.0</y>
		</point>
		<point>
			<x>79.0</x>
			<y>314.814285714</y>
		</point>
		<point>
			<x>80.0</x>
			<y>314.870689655</y>
		</point>
		<point>
			<x>80.8211382114</x>
			<y>314.0</y>
		</point>
		<point>
			<x>81.0</x>
			<y>313.808695652</y>
		</point>
		<point>
			<x>82.0</x>
			<y>313.8</y>
		</point>
		<point>
			<x>83.0</x>
			<y>313.853556485</y>
		</point>
		<point>
			<x>83.8</x>
			<y>313.0</y>
		</point>
		<point>
			<x>83.8008130081</x>
			<y>312.0</y>
		</point>
		<point>
			<x>83.7943548387</x>
			<y>311.0</y>
		</point>
		<point>
			<x>83.8192771084</x>
			<y>310.0</y>
		</point>
		<point>
			<x>83.8</x>
			<y>309.0</y>
		</point>
		<point>
			<x>84.0</x>
			<y>308.783898305</y>
		</point>
		<point>
			<x>85.0</x>
			<y>308.816</y>
		</point>
		<point>
			<x>85.8</x>
			<y>308.0</y>
		</point>
		<point>
			<x>85.8028169014</x>
			<y>307.0</y>
		</point>
		<point>
			<x>85.7916666667</x>
			<y>306.0</y>
		</point>
		<point>
			<x>85.820083682</x>
			<y>305.0</y>
		</point>
		<point>
			<x>85.0</x>
			<y>304.136563877</y>
		</point>
		<point>
			<x>84.8680851064</x>
			<y>304.0</y>
		</point>
		<point>
			<x>84.8211382114</x>
			<y>303.0</y>
		</point>
		<point>
			<x>84.0</x>
			<y>302.201581028</y>
		</point>
		<point>
			<x>83.8</x>
			<y>302.0</y>
		</point>
		<point>
			<x>83.8603603604</x>
			<y>301.0</y>
		</point>
		<point>
			<x>83.7907949791</x>
			<y>300.0</y>
		</point>
		<point>
			<x>83.8</x>
			<y>299.0</y>
		</point>
		<point>
			<x>83.8340425532</x>
			<y>298.0</y>
		</point>
		<point>
			<x>83.0</x>
			<y>297.206477733</y>
		</point>
		<point>
			<x>82.0</x>
			<y>297.15</y>
		</point>
		<point>
			<x>81.8317757009</x>
			<y>297.0</y>
		</point>
		<point>
			<x>81.0</x>
			<y>296.198198198</y>
		</point>
		<point>
			<x>80.8181818182</x>
			<y>296.0</y>
		</point>
		<point>
			<x>80.0</x>
			<y>295.127753304</y>
		</point>
		<point>
			<x>79.8669724771</x>
			<y>295.0</y>
		</point>
		<point>
			<x>79.0</x>
			<y>294.202531646</y>
		</point>
		<point>
			<x>78.7948717949</x>
			<y>294.0</y>
		</point>
		<point>
			<x>78.0</x>
			<y>293.134883721</y>
		</point>
		<point>
			<x>77.8681818182</x>
			<y>293.0</y>
		</point>
		<point>
			<x>77.0</x>
			<y>292.210743802</y>
		</point>
		<point>
			<x>76.0</x>
			<y>292.191836735</y>
		</point>
		<point>
			<x>75.0</x>
			<y>292.202380952</y>
		</point>
		<point>
			<x>74.0</x>
			<y>292.13559322</y>
		</point>
		<point>
			<x>73.8468899522</x>
			<y>292.0</y>
		</point>
		<point>
			<x>74.0</x>
			<y>291.855855856</y>
		</point>
		<point>
			<x>74.8482142857</x>
			<y>291.0</y>
		</point>
		<point>
			<x>74.8095238095</x>
			<y>290.0</y>
		</point>
		<point>
			<x>75.0</x>
			<y>289.792207792</y>
		</point>
		<point>
			<x>76.0</x>
			<y>289.826086957</y>
		</point>
		<point>
			<x>77.0</x>
			<y>289.85</y>
		</point>
		<point>
			<x>78.0</x>
			<y>289.792682927</y>
		</point>
		<point>
			<x>79.0</x>
			<y>289.812749004</y>
		</point>
		<point>
			<x>80.0</x>
			<y>289.835443038</y>
		</point>
		<point>
			<x>80.7951807229</x>
			<y>289.0</y>
		</point>
		<point>
			<x>81.0</x>
			<y>288.790983607</y>
		</point>
		<point>
			<x>81.2007874016</x>
			<y>289.0</y>
		</point>
		<point>
			<x>82.0</x>
			<y>289.80876494</y>
		</point>
		<point>
			<x>83.0</x>
			<y>289.793522267</y>
		</point>
		<point>
			<x>83.7935222672</x>
			<y>289.0</y>
		</point>
		<point>
			<x>83.8</x>
			<y>288.0</y>
		</point>
		<point>
			<x>84.0</x>
			<y>287.8</y>
		</point>
		<point>
			<x>85.0</x>
			<y>287.818965517</y>
		</point>
		<point>
			<x>85.8154506438</x>
			<y>287.0</y>
		</point>
		<point>
			<x>85.8326530612</x>
			<y>286.0</y>
		</point>
		<point>
			<x>85.8170212766</x>
			<y>285.0</y>
		</point>
		<point>
			<x>85.8</x>
			<y>284.0</y>
		</point>
		<point>
			<x>85.8</x>
			<y>283.0</y>
		</point>
		<point>
			<x>85.0</x>
			<y>282.2</y>
		</point>
		<point>
			<x>84.8</x>
			<y>282.0</y>
		</point>
		<point>
			<x>84.0</x>
			<y>281.124463519</y>
		</point>
		<point>
			<x>83.8675799087</x>
			<y>281.0</y>
		</point>
		<point>
			<x>83.8</x>
			<y>280.0</y>
		</point>
		<point>
			<x>83.0</x>
			<y>279.193675889</y>
		</point>
		<point>
			<x>82.0</x>
			<y>279.208163265</y>
		</point>
		<point>
			<x>81.0</x>
			<y>279.206477733</y>
		</point>
		<point>
			<x>80.0</x>
			<y>279.19047619</y>
		</point>
		<point>
			<x>79.0</x>
			<y>279.188</y>
		</point>
		<point>
			<x>78.0</x>
			<y>279.196850394</y>
		</point>
		<point>
			<x>77.0</x>
			<y>279.204</y>
		</point>
		<point>
			<x>76.0</x>
			<y>279.203252033</y>
		</point>
		<point>
			<x>75.1833333333</x>
			<y>280.0</y>
		</point>
		<point>
			<x>75.2</x>
			<y>281.0</y>
		</point>
		<point>
			<x>75.0</x>
			<y>281.200787402</y>
		</point>
		<point>
			<x>74.0</x>
			<y>281.2</y>
		</point>
		<point>
			<x>73.8</x>
			<y>281.0</y>
		</point>
		<point>
			<x>73.0</x>
			<y>280.2</y>
		</point>
		<point>
			<x>72.0</x>
			<y>280.193675889</y>
		</point>
		<point>
			<x>71.8024193548</x>
			<y>280.0</y>
		</point>
		<point>
			<x>71.0</x>
			<y>279.200803213</y>
		</point>
		<point>
			<x>70.0</x>
			<y>279.193675889</y>
		</point>
		<point>
			<x>69.8</x>
			<y>279.0</y>
		</point>
		<point>
			<x>69.0</x>
			<y>278.147826087</y>
		</point>
		<point>
			<x>68.0</x>
			<y>278.215189873</y>
		</point>
		<point>
			<x>67.1506849315</x>
			<y>279.0</y>
		</point>
		<point>
			<x>67.0</x>
			<y>279.148648649</y>
		</point>
		<point>
			<x>66.0</x>
			<y>279.2</y>
		</point>
		<point>
			<x>65.2</x>
			<y>280.0</y>
		</point>
		<point>
			<x>65.0</x>
			<y>280.2</y>
		</point>
		<point>
			<x>64.2</x>
			<y>281.0</y>
		</point>
		<point>
			<x>64.0</x>
			<y>281.203187251</y>
		</point>
		<point>
			<x>63.0</x>
			<y>281.123762376</y>
		</point>
		<point>
			<x>62.1105527638</x>
			<y>282.0</y>
		</point>
		<point>
			<x>62.0</x>
			<y>282.102325581</y>
		</point>
		<point>
			<x>61.0</x>
			<y>282.216101695</y>
		</point>
		<point>
			<x>60.0</x>
			<y>282.175732218</y>
		</point>
		<point>
			<x>59.2056451613</x>
			<y>283.0</y>
		</point>
		<point>
			<x>59.2125</x>
			<y>284.0</y>
		</point>
		<point>
			<x>59.1968503937</x>
			<y>285.0</y>
		</point>
		<point>
			<x>59.2122641509</x>
			<y>286.0</y>
		</point>
		<point>
			<x>59.1904761905</x>
			<y>287.0</y>
		</point>
		<point>
			<x>59.2064777328</x>
			<y>288.0</y>
		</point>
		<point>
			<x>59.1967871486</x>
			<y>289.0</y>
		</point>
		<point>
			<x>59.1924686192</x>
			<y>290.0</y>
		</point>
		<point>
			<x>60.0</x>
			<y>290.850220264</y>
		</point>
		<point>
			<x>60.1471861472</x>
			<y>291.0</y>
		</point>
		<point>
			<x>60.1898734177</x>
			<y>292.0</y>
		</point>
		<point>
			<x>61.0</x>
			<y>292.810126582</y>
		</point>
		<point>
			<x>61.1807228916</x>
			<y>293.0</y>
		</point>
		<point>
			<x>61.2</x>
			<y>294.0</y>
		</point>
		<point>
			<x>61.192</x>
			<y>295.0</y>
		</point>
		<point>
			<x>61.0</x>
			<y>295.19047619</y>
		</point>
		<point>
			<x>60.2</x>
			<y>296.0</y>
		</point>
		<point>
			<x>60.1731601732</x>
			<y>297.0</y>
		</point>
		<point>
			<x>60.1590909091</x>
			<y>298.0</y>
		</point>
		<point>
			<x>60.2073170732</x>
			<y>299.0</y>
		</point>
		<point>
			<x>61.0</x>
			<y>299.836909871</y>
		</point>
		<point>
			<x>61.1610169492</x>
			<y>300.0</y>
		</point>
		<point>
			<x>62.0</x>
			<y>300.857142857</y>
		</point>
		<point>
			<x>63.0</x>
			<y>300.80952381</y>
		</point>
		<point>
			<x>64.0</x>
			<y>300.800829876</y>
		</point>
		<point>
			<x>65.0</x>
			<y>300.805785124</y>
		</point>
		<point>
			<x>65.189516129</x>
			<y>301.0</y>
		</point>
		<point>
			<x>66.0</x>
			<y>301.797619048</y>
		</point>
		<point>
			<x>67.0</x>
			<y>301.811158798</y>
		</point>
		<point>
			<x>67.8325991189</x>
			<y>301.0</y>
		</point>
		<point>
			<x>68.0</x>
			<y>300.842975207</y>
		</point>
		<point>
			<x>69.0</x>
			<y>300.8</y>
		</point>
		<point>
			<x>70.0</x>
			<y>300.844827586</y>
		</point>
		<point>
			<x>71.0</x>
			<y>300.817813765</y>
		</point>
		<point>
			<x>72.0</x>
			<y>300.876777251</y>
		</point>
		<point>
			<x>73.0</x>
			<y>300.8</y>
		</point>
		<point>
			<x>74.0</x>
			<y>300.807228916</y>
		</point>
		<point>
			<x>74.192</x>
			<y>301.0</y>
		</point>
		<point>
			<x>75.0</x>
			<y>301.81124498</y>
		</point>
		<point>
			<x>75.187250996</x>
			<y>302.0</y>
		</point>
		<point>
			<x>75.2023809524</x>
			<y>303.0</y>
		</point>
		<point>
			<x>75.1936758893</x>
			<y>304.0</y>
		</point>
		<point>
			<x>75.187755102</x>
			<y>305.0</y>
		</point>
		<point>
			<x>75.147826087</x>
			<y>306.0</y>
		</point>
		<point>
			<x>75.2</x>
			<y>307.0</y>
		</point>
		<point>
			<x>75.1479820628</x>
			<y>308.0</y>
		</point>
		<point>
			<x>75.0</x>
			<y>308.15942029</y>
		</point>
		<point>
			<x>74.0</x>
			<y>308.147058824</y>
		</point>
		<point>
			<x>73.0</x>
			<y>308.2</y>
		</point>
		<point>
			<x>72.0</x>
			<y>308.205645161</y>
		</point>
		<point>
			<x>71.0</x>
			<y>308.211864407</y>
		</point>
		<point>
			<x>70.2017167382</x>
			<y>309.0</y>
		</point>
		<point>
			<x>70.0</x>
			<y>309.207048458</y>
		</point>
		<point>
			<x>69.0</x>
			<y>309.2</y>
		</point>
		<point>
			<x>68.0</x>
			<y>309.163934426</y>
		</point>
		<point>
			<x>67.8360655738</x>
			<y>309.0</y>
		</point>
		<point>
			<x>67.8008298755</x>
			<y>308.0</y>
		</point>
		<point>
			<x>67.8</x>
			<y>307.0</y>
		</point>
		<point>
			<x>67.8312236287</x>
			<y>306.0</y>
		</point>
		<point>
			<x>67.8</x>
			<y>305.0</y>
		</point>
		<point>
			<x>67.0</x>
			<y>304.2</y>
		</point>
		<point>
			<x>66.0</x>
			<y>304.147826087</y>
		</point>
		<point>
			<x>65.0</x>
			<y>304.2</y>
		</point>
		<point>
			<x>64.0</x>
			<y>304.186721992</y>
		</point>
		<point>
			<x>63.0</x>
			<y>304.165289256</y>
		</point>
		<point>
			<x>62.0</x>
			<y>304.193675889</y>
		</point>
		<point>
			<x>61.1774193548</x>
			<y>305.0</y>
		</point>
		<point>
			<x>61.0</x>
			<y>305.177419355</y>
		</point>
		<point>
			<x>60.0</x>
			<y>305.207317073</y>
		</point>
		<point>
			<x>59.2008196721</x>
			<y>306.0</y>
		</point>
		<point>
			<x>59.204</x>
			<y>307.0</y>
		</point>
		<point>
			<x>59.1785714286</x>
			<y>308.0</y>
		</point>
		<point>
			<x>59.0</x>
			<y>308.164609053</y>
		</point>
		<point>
			<x>58.0</x>
			<y>308.2</y>
		</point>
		<point>
			<x>57.2</x>
			<y>309.0</y>
		</point>
		<point>
			<x>57.1327433628</x>
			<y>310.0</y>
		</point>
		<point>
			<x>57.1934156379</x>
			<y>311.0</y>
		</point>
		<point>
			<x>57.1542056075</x>
			<y>312.0</y>
		</point>
		<point>
			<x>58.0</x>
			<y>312.849765258</y>
		</point>
		<point>
			<x>59.0</x>
			<y>312.808</y>
		</point>
		<point>
			<x>59.2253521127</x>
			<y>313.0</y>
		</point>
		<point>
			<x>59.1673469388</x>
			<y>314.0</y>
		</point>
		<point>
			<x>59.1957446809</x>
			<y>315.0</y>
		</point>
		<point>
			<x>60.0</x>
			<y>315.7875</y>
		</point>
		<point>
			<x>61.0</x>
			<y>315.85645933</y>
		</point>
		<point>
			<x>61.1428571429</x>
			<y>316.0</y>
		</point>
		<point>
			<x>62.0</x>
			<y>316.782608696</y>
		</point>
		<point>
			<x>63.0</x>
			<y>316.8</y>
		</point>
		<point>
			<x>64.0</x>
			<y>316.798418972</y>
		</point>
		<point>
			<x>65.0</x>
			<y>316.798418972</y>
		</point>
		<point>
			<x>66.0</x>
			<y>316.798418972</y>
		</point>
		<point>
			<x>67.0</x>
			<y>316.798418972</y>
		</point>
		<point>
			<x>68.0</x>
			<y>316.798418972</y>
		</point>
		<point>
			<x>69.0</x>
			<y>316.798418972</y>
		</point>
		<point>
			<x>70.0</x>
			<y>316.798418972</y>
		</point>
		<point>
			<x>71.0</x>
			<y>316.798418972</y>
		</point>
		<point>
			<x>72.0</x>
			<y>316.804979253</y>
		</point>
		<point>
			<x>73.0</x>
			<y>316.8</y>
		</point>
		<point>
			<x>74.0</x>
			<y>316.790598291</y>
		</point>
		<point>
			<x>75.0</x>
			<y>316.825531915</y>
		</point>
		<point>
			<x>76.0</x>
			<y>316.797468354</y>
		</point>
		<point>
			<x>76.8669724771</x>
			<y>316.0</y>
		</point>
	</contour>
	<contour>
		<point>
			<x>107.8</x>
			<y>311.0</y>
		</point>
		<point>
			<x>107.857142857</x>
			<y>310.0</y>
		</point>
		<point>
			<x>108.0</x>
			<y>309.854077253</y>
		</point>
		<point>
			<x>108.808943089</x>
			<y>309.0</y>
		</point>
		<point>
			<x>109.0</x>
			<y>308.805785124</y>
		</point>
		<point>
			<x>110.0</x>
			<y>308.794979079</y>
		</point>
		<point>
			<x>111.0</x>
			<y>308.844827586</y>
		</point>
		<point>
			<x>111.803278689</x>
			<y>308.0</y>
		</point>
		<point>
			<x>112.0</x>
			<y>307.79916318</y>
		</point>
		<point>
			<x>112.802521008</x>
			<y>307.0</y>
		</point>
		<point>
			<x>113.0</x>
			<y>306.81124498</y>
		</point>
		<point>
			<x>114.0</x>
			<y>306.827433628</y>
		</point>
		<point>
			<x>114.795744681</x>
			<y>306.0</y>
		</point>
		<point>
			<x>115.0</x>
			<y>305.806451613</y>
		</point>
		<point>
			<x>115.796812749</x>
			<y>305.0</y>
		</point>
		<point>
			<x>115.834782609</x>
			<y>304.0</y>
		</point>
		<point>
			<x>115.797619048</x>
			<y>303.0</y>
		</point>
		<point>
			<x>115.797619048</x>
			<y>302.0</y>
		</point>
		<point>
			<x>115.797619048</x>
			<y>301.0</y>
		</point>
		<point>
			<x>115.797619048</x>
			<y>300.0</y>
		</point>
		<point>
			<x>115.797619048</x>
			<y>299.0</y>
		</point>
		<point>
			<x>115.797619048</x>
			<y>298.0</y>
		</point>
		<point>
			<x>115.797619048</x>
			<y>297.0</y>
		</point>
		<point>
			<x>115.797619048</x>
			<y>296.0</y>
		</point>
		<point>
			<x>115.818584071</x>
			<y>295.0</y>
		</point>
		<point>
			<x>115.816</x>
			<y>294.0</y>
		</point>
		<point>
			<x>115.8</x>
			<y>293.0</y>
		</point>
		<point>
			<x>115.0</x>
			<y>292.153526971</y>
		</point>
		<point>
			<x>114.0</x>
			<y>292.181451613</y>
		</point>
		<point>
			<x>113.814814815</x>
			<y>292.0</y>
		</point>
		<point>
			<x>113.887850467</x>
			<y>291.0</y>
		</point>
		<point>
			<x>113.0</x>
			<y>290.191489362</y>
		</point>
		<point>
			<x>112.819277108</x>
			<y>290.0</y>
		</point>
		<point>
			<x>112.0</x>
			<y>289.157024793</y>
		</point>
		<point>
			<x>111.842975207</x>
			<y>289.0</y>
		</point>
		<point>
			<x>111.0</x>
			<y>288.167346939</y>
		</point>
		<point>
			<x>110.0</x>
			<y>288.193693694</y>
		</point>
		<point>
			<x>109.824489796</x>
			<y>288.0</y>
		</point>
		<point>
			<x>109.0</x>
			<y>287.195219124</y>
		</point>
		<point>
			<x>108.0</x>
			<y>287.193675889</y>
		</point>
		<point>
			<x>107.806324111</x>
			<y>287.0</y>
		</point>
		<point>
			<x>107.7875</x>
			<y>286.0</y>
		</point>
		<point>
			<x>107.0</x>
			<y>285.202531646</y>
		</point>
		<point>
			<x>106.0</x>
			<y>285.2</y>
		</point>
		<point>
			<x>105.0</x>
			<y>285.151898734</y>
		</point>
		<point>
			<x>104.845493562</x>
			<y>285.0</y>
		</point>
		<point>
			<x>104.0</x>
			<y>284.179166667</y>
		</point>
		<point>
			<x>103.0</x>
			<y>284.202380952</y>
		</point>
		<point>
			<x>102.0</x>
			<y>284.202380952</y>
		</point>
		<point>
			<x>101.0</x>
			<y>284.202380952</y>
		</point>
		<point>
			<x>100.0</x>
			<y>284.202380952</y>
		</point>
		<point>
			<x>99.0</x>
			<y>284.202380952</y>
		</point>
		<point>
			<x>98.0</x>
			<y>284.202380952</y>
		</point>
		<point>
			<x>97.0</x>
			<y>284.202380952</y>
		</point>
		<point>
			<x>96.0</x>
			<y>284.202380952</y>
		</point>
		<point>
			<x>95.0</x>
			<y>284.157446809</y>
		</point>
		<point>
			<x>94.0</x>
			<y>284.204</y>
		</point>
		<point>
			<x>93.0</x>
			<y>284.179824561</y>
		</point>
		<point>
			<x>92.0</x>
			<y>284.179591837</y>
		</point>
		<point>
			<x>91.0</x>
			<y>284.177966102</y>
		</point>
		<point>
			<x>90.0</x>
			<y>284.209016393</y>
		</point>
		<point>
			<x>89.0</x>
			<y>284.147058824</y>
		</point>
		<point>
			<x>88.1646090535</x>
			<y>285.0</y>
		</point>
		<point>
			<x>88.1975308642</x>
			<y>286.0</y>
		</point>
		<point>
			<x>88.0</x>
			<y>286.192</y>
		</point>
		<point>
			<x>87.2015810277</x>
			<y>287.0</y>
		</point>
		<point>
			<x>87.1983805668</x>
			<y>288.0</y>
		</point>
		<point>
			<x>87.0</x>
			<y>288.193675889</y>
		</point>
		<point>
			<x>86.187250996</x>
			<y>289.0</y>
		</point>
		<point>
			<x>86.2207792208</x>
			<y>290.0</y>
		</point>
		<point>
			<x>86.1483050847</x>
			<y>291.0</y>
		</point>
		<point>
			<x>86.0</x>
			<y>291.14957265</y>
		</point>
		<point>
			<x>85.1742738589</x>
			<y>292.0</y>
		</point>
		<point>
			<x>85.2098765432</x>
			<y>293.0</y>
		</point>
		<point>
			<x>85.1776859504</x>
			<y>294.0</y>
		</point>
		<point>
			<x>85.2</x>
			<y>295.0</y>
		</point>
		<point>
			<x>85.2056451613</x>
			<y>296.0</y>
		</point>
		<point>
			<x>85.1428571429</x>
			<y>297.0</y>
		</point>
		<point>
			<x>85.2090163934</x>
			<y>298.0</y>
		</point>
		<point>
			<x>85.2</x>
			<y>299.0</y>
		</point>
		<point>
			<x>85.1829268293</x>
			<y>300.0</y>
		</point>
		<point>
			<x>86.0</x>
			<y>300.810483871</y>
		</point>
		<point>
			<x>86.187250996</x>
			<y>301.0</y>
		</point>
		<point>
			<x>86.1782608696</x>
			<y>302.0</y>
		</point>
		<point>
			<x>87.0</x>
			<y>302.818181818</y>
		</point>
		<point>
			<x>87.1707317073</x>
			<y>303.0</y>
		</point>
		<point>
			<x>87.1900826446</x>
			<y>304.0</y>
		</point>
		<point>
			<x>87.1926229508</x>
			<y>305.0</y>
		</point>
		<point>
			<x>87.2048192771</x>
			<y>306.0</y>
		</point>
		<point>
			<x>88.0</x>
			<y>306.81147541</y>
		</point>
		<point>
			<x>88.184</x>
			<y>307.0</y>
		</point>
		<point>
			<x>89.0</x>
			<y>307.8</y>
		</point>
		<point>
			<x>89.2098765432</x>
			<y>308.0</y>
		</point>
		<point>
			<x>90.0</x>
			<y>308.849557522</y>
		</point>
		<point>
			<x>91.0</x>
			<y>308.8</y>
		</point>
		<point>
			<x>91.2</x>
			<y>309.0</y>
		</point>
		<point>
			<x>91.1718061674</x>
			<y>310.0</y>
		</point>
		<point>
			<x>92.0</x>
			<y>310.820960699</y>
		</point>
		<point>
			<x>93.0</x>
			<y>310.805194805</y>
		</point>
		<point>
			<x>94.0</x>
			<y>310.836065574</y>
		</point>
		<point>
			<x>95.0</x>
			<y>310.800813008</y>
		</point>
		<point>
			<x>95.196</x>
			<y>311.0</y>
		</point>
		<point>
			<x>96.0</x>
			<y>311.813765182</y>
		</point>
		<point>
			<x>97.0</x>
			<y>311.807377049</y>
		</point>
		<point>
			<x>98.0</x>
			<y>311.80952381</y>
		</point>
		<point>
			<x>99.0</x>
			<y>311.807228916</y>
		</point>
		<point>
			<x>100.0</x>
			<y>311.803212851</y>
		</point>
		<point>
			<x>101.0</x>
			<y>311.802371542</y>
		</point>
		<point>
			<x>102.0</x>
			<y>311.795180723</y>
		</point>
		<point>
			<x>103.0</x>
			<y>311.797619048</y>
		</point>
		<point>
			<x>104.0</x>
			<y>311.8</y>
		</point>
		<point>
			<x>105.0</x>
			<y>311.8</y>
		</point>
		<point>
			<x>106.0</x>
			<y>311.790983607</y>
		</point>
		<point>
			<x>107.0</x>
			<y>311.806324111</y>
		</point>
		<point>
			<x>107.8</x>
			<y>311.0</y>
		</point>
	</contour>
	<contour>
		<point>
			<x>99.0</x>
			<y>304.1625</y>
		</point>
		<point>
			<x>98.0</x>
			<y>304.210526316</y>
		</point>
		<point>
			<x>97.8072289157</x>
			<y>304.0</y>
		</point>
		<point>
			<x>97.0</x>
			<y>303.12987013</y>
		</point>
		<point>
			<x>96.8672566372</x>
			<y>303.0</y>
		</point>
		<point>
			<x>96.8</x>
			<y>302.0</y>
		</point>
		<point>
			<x>96.0</x>
			<y>301.2</y>
		</point>
		<point>
			<x>95.7892561983</x>
			<y>301.0</y>
		</point>
		<point>
			<x>95.0</x>
			<y>300.190677966</y>
		</point>
		<point>
			<x>94.7826086957</x>
			<y>300.0</y>
		</point>
		<point>
			<x>94.8063241107</x>
			<y>299.0</y>
		</point>
		<point>
			<x>94.8242677824</x>
			<y>298.0</y>
		</point>
		<point>
			<x>94.849137931</x>
			<y>297.0</y>
		</point>
		<point>
			<x>94.7984189723</x>
			<y>296.0</y>
		</point>
		<point>
			<x>95.0</x>
			<y>295.796812749</y>
		</point>
		<point>
			<x>95.796812749</x>
			<y>295.0</y>
		</point>
		<point>
			<x>96.0</x>
			<y>294.795180723</y>
		</point>
		<point>
			<x>96.8284518828</x>
			<y>294.0</y>
		</point>
		<point>
			<x>96.7892561983</x>
			<y>293.0</y>
		</point>
		<point>
			<x>97.0</x>
			<y>292.7875</y>
		</point>
		<point>
			<x>98.0</x>
			<y>292.841666667</y>
		</point>
		<point>
			<x>99.0</x>
			<y>292.833333333</y>
		</point>
		<point>
			<x>99.8227848101</x>
			<y>292.0</y>
		</point>
		<point>
			<x>100.0</x>
			<y>291.826446281</y>
		</point>
		<point>
			<x>101.0</x>
			<y>291.799212598</y>
		</point>
		<point>
			<x>102.0</x>
			<y>291.834782609</y>
		</point>
		<point>
			<x>102.163793103</x>
			<y>292.0</y>
		</point>
		<point>
			<x>103.0</x>
			<y>292.791836735</y>
		</point>
		<point>
			<x>104.0</x>
			<y>292.8</y>
		</point>
		<point>
			<x>105.0</x>
			<y>292.798418972</y>
		</point>
		<point>
			<x>106.0</x>
			<y>292.80952381</y>
		</point>
		<point>
			<x>107.0</x>
			<y>292.821782178</y>
		</point>
		<point>
			<x>107.15720524</x>
			<y>293.0</y>
		</point>
		<point>
			<x>107.196850394</x>
			<y>294.0</y>
		</point>
		<point>
			<x>107.198312236</x>
			<y>295.0</y>
		</point>
		<point>
			<x>107.201581028</x>
			<y>296.0</y>
		</point>
		<point>
			<x>107.2</x>
			<y>297.0</y>
		</point>
		<point>
			<x>108.0</x>
			<y>297.806324111</y>
		</point>
		<point>
			<x>108.242574257</x>
			<y>298.0</y>
		</point>
		<point>
			<x>108.142857143</x>
			<y>299.0</y>
		</point>
		<point>
			<x>108.187250996</x>
			<y>300.0</y>
		</point>
		<point>
			<x>108.0</x>
			<y>300.192622951</y>
		</point>
		<point>
			<x>107.205645161</x>
			<y>301.0</y>
		</point>
		<point>
			<x>107.0</x>
			<y>301.200787402</y>
		</point>
		<point>
			<x>106.184738956</x>
			<y>302.0</y>
		</point>
		<point>
			<x>106.0</x>
			<y>302.190871369</y>
		</point>
		<point>
			<x>105.0</x>
			<y>302.2</y>
		</point>
		<point>
			<x>104.0</x>
			<y>302.204819277</y>
		</point>
		<point>
			<x>103.0</x>
			<y>302.2</y>
		</point>
		<point>
			<x>102.2</x>
			<y>303.0</y>
		</point>
		<point>
			<x>102.0</x>
			<y>303.211618257</y>
		</point>
		<point>
			<x>101.0</x>
			<y>303.2</y>
		</point>
		<point>
			<x>100.0</x>
			<y>303.168949772</y>
		</point>
		<point>
			<x>99.1764705882</x>
			<y>304.0</y>
		</point>
		<point>
			<x>99.0</x>
			<y>304.1625</y>
		</point>
	</contour>
</manuscript>
